[{"size": 3500, "ticker": "QQQ", "price": "673.95", "sale_cond_codes": null, "premium": "2358825.00", "volume": 39026756, "executed_at": "2026-05-01T21:54:38Z", "canceled": false, "nbbo_ask": "673.95", "nbbo_bid": "673.9", "ext_hour_sold_codes": "extended_hours_trade", "market_center": "L", "nbbo_ask_quantity": 520, "nbbo_bid_quantity": 59, "tracking_id": 10501273917413, "trade_code": null, "trade_settlement": "regular", "trf_executed_at": "2026-05-01T21:54:38Z"}, {"size": 1200, "ticker": "INTC", "price": "99.98", "sale_cond_codes": null, "premium": "119976.00", "volume": 157322308, "executed_at": "2026-05-01T21:54:34Z", "canceled": false, "nbbo_ask": "99.98", "nbbo_bid": "99.89", "ext_hour_sold_codes": "extended_hours_trade", "market_center": "L", "nbbo_ask_quantity": 24, "nbbo_bid_quantity": 506, "tracking_id": 25812832323761, "trade_code": null, "trade_settlement": "regular", "trf_executed_at": "2026-05-01T21:54:34Z"}, {"size": 2750, "ticker": "INTC", "price": "99.97", "sale_cond_codes": null, "premium": "274917.50", "volume": 157316170, "executed_at": "2026-05-01T21:54:33Z", "canceled": false, "nbbo_ask": "99.98", "nbbo_bid": "99.89", "ext_hour_sold_codes": "extended_hours_trade", "market_center": "L", "nbbo_ask_quantity": 24, "nbbo_bid_quantity": 506, "tracking_id": 25812832322758, "trade_code": null, "trade_settlement": "regular", "trf_executed_at": "2026-05-01T21:54:33Z"}, {"size": 6459, "ticker": "BOXX", "price": "116.5799", "sale_cond_codes": null, "premium": "752989.5741", "volume": 2075254, "executed_at": "2026-05-01T21:54:32Z", "canceled": false, "nbbo_ask": "116.6", "nbbo_bid": "116.56", "ext_hour_sold_codes": "extended_hours_trade", "market_center": "L", "nbbo_ask_quantity": 927, "nbbo_bid_quantity": 291, "tracking_id": 6622918442849, "trade_code": null, "trade_settlement": "regular", "trf_executed_at": "2026-05-01T21:54:32Z"}, {"size": 15600, "ticker": "SOXS", "price": "12.99", "sale_cond_codes": null, "premium": "202644.00", "volume": 123457104, "executed_at": "2026-05-01T21:54:31Z", "canceled": false, "nbbo_ask": "13", "nbbo_bid": "12.99", "ext_hour_sold_codes": "extended_hours_trade", "market_center": "L", "nbbo_ask_quantity": 67, "nbbo_bid_quantity": 421, "tracking_id": 12764721675342, "trade_code": null, "trade_settlement": "regular", "trf_executed_at": "2026-05-01T21:54:31Z"}, {"size": 2000, "ticker": "NFLX", "price": "92.0174", "sale_cond_codes": null, "premium": "184034.8000", "volume": 30314886, "executed_at": "2026-05-01T21:54:23Z", "canceled": false, "nbbo_ask": "92.02", "nbbo_bid": "92", "ext_hour_sold_codes": "extended_hours_trade", "market_center": "L", "nbbo_ask_quantity": 5, "nbbo_bid_quantity": 1, "tracking_id": 30863713852442, "trade_code": null, "trade_settlement": "regular", "trf_executed_at": "2026-05-01T21:54:23Z"}, {"size": 6000, "ticker": "GME", "price": "27.4478", "sale_cond_codes": null, "premium": "164686.8000", "volume": 18103096, "executed_at": "2026-05-01T21:54:23Z", "canceled": false, "nbbo_ask": "27.5", "nbbo_bid": "27.44", "ext_hour_sold_codes": "extended_hours_trade", "market_center": "L", "nbbo_ask_quantity": 4140, "nbbo_bid_quantity": 364, "tracking_id": 32504391359298, "trade_code": null, "trade_settlement": "regular", "trf_executed_at": "2026-05-01T21:54:23Z"}, {"size": 1000, "ticker": "QQQ", "price": "674", "sale_cond_codes": null, "premium": "674000", "volume": 39020130, "executed_at": "2026-05-01T21:54:19Z", "canceled": false, "nbbo_ask": "674", "nbbo_bid": "673.98", "ext_hour_sold_codes": "extended_hours_trade", "market_center": "L", "nbbo_ask_quantity": 56, "nbbo_bid_quantity": 4120, "tracking_id": 10501273898621, "trade_code": null, "trade_settlement": "regular", "trf_executed_at": "2026-05-01T21:54:19Z"}, {"size": 130, "ticker": "SNDK", "price": "1188.13", "sale_cond_codes": null, "premium": "154456.90", "volume": 22996878, "executed_at": "2026-05-01T21:54:15Z", "canceled": false, "nbbo_ask": "1188.91", "nbbo_bid": "1188.3", "ext_hour_sold_codes": "extended_hours_trade", "market_center": "L", "nbbo_ask_quantity": 4, "nbbo_bid_quantity": 7, "tracking_id": 18270869732644, "trade_code": null, "trade_settlement": "regular", "trf_executed_at": "2026-05-01T21:54:15Z"}, {"size": 657, "ticker": "CI", "price": "282.5", "sale_cond_codes": null, "premium": "185602.5", "volume": 1519935, "executed_at": "2026-05-01T21:54:14Z", "canceled": false, "nbbo_ask": "286", "nbbo_bid": "282.1", "ext_hour_sold_codes": "extended_hours_trade", "market_center": "L", "nbbo_ask_quantity": 5, "nbbo_bid_quantity": 100, "tracking_id": 27092732558131, "trade_code": null, "trade_settlement": "regular", "trf_executed_at": "2026-05-01T21:54:14Z"}, {"size": 212, "ticker": "META", "price": "608.5", "sale_cond_codes": null, "premium": "129002.0", "volume": 21343484, "executed_at": "2026-05-01T21:54:14Z", "canceled": false, "nbbo_ask": "608.51", "nbbo_bid": "608.42", "ext_hour_sold_codes": "extended_hours_trade", "market_center": "L", "nbbo_ask_quantity": 121, "nbbo_bid_quantity": 3, "tracking_id": 32508686317632, "trade_code": null, "trade_settlement": "regular", "trf_executed_at": "2026-05-01T21:54:14Z"}, {"size": 4000, "ticker": "META", "price": "608.5", "sale_cond_codes": null, "premium": "2434000.0", "volume": 21342512, "executed_at": "2026-05-01T21:54:14Z", "canceled": false, "nbbo_ask": "608.51", "nbbo_bid": "608.42", "ext_hour_sold_codes": "extended_hours_trade", "market_center": "L", "nbbo_ask_quantity": 121, "nbbo_bid_quantity": 3, "tracking_id": 32508686317631, "trade_code": null, "trade_settlement": "regular", "trf_executed_at": "2026-05-01T21:54:14Z"}, {"size": 680, "ticker": "META", "price": "608.5", "sale_cond_codes": null, "premium": "413780.0", "volume": 21343272, "executed_at": "2026-05-01T21:54:14Z", "canceled": false, "nbbo_ask": "608.51", "nbbo_bid": "608.42", "ext_hour_sold_codes": "extended_hours_trade", "market_center": "L", "nbbo_ask_quantity": 121, "nbbo_bid_quantity": 3, "tracking_id": 32508686317631, "trade_code": null, "trade_settlement": "regular", "trf_executed_at": "2026-05-01T21:54:14Z"}, {"size": 20333, "ticker": "CRML", "price": "12.44", "sale_cond_codes": null, "premium": "252942.52", "volume": 13842969, "executed_at": "2026-05-01T21:54:13Z", "canceled": false, "nbbo_ask": "12.44", "nbbo_bid": "12.41", "ext_hour_sold_codes": "extended_hours_trade", "market_center": "L", "nbbo_ask_quantity": 90, "nbbo_bid_quantity": 8, "tracking_id": 21535044875774, "trade_code": null, "trade_settlement": "regular", "trf_executed_at": "2026-05-01T21:54:13Z"}, {"size": 1200, "ticker": "EBAY", "price": "119.4176", "sale_cond_codes": null, "premium": "143301.1200", "volume": 11500179, "executed_at": "2026-05-01T21:54:12Z", "canceled": false, "nbbo_ask": "119.48", "nbbo_bid": "118.96", "ext_hour_sold_codes": "extended_hours_trade", "market_center": "L", "nbbo_ask_quantity": 100, "nbbo_bid_quantity": 1, "tracking_id": 30859418874758, "trade_code": null, "trade_settlement": "regular", "trf_executed_at": "2026-05-01T21:54:12Z"}, {"size": 592, "ticker": "NVDA", "price": "198.25", "sale_cond_codes": null, "premium": "117364.00", "volume": 128208317, "executed_at": "2026-05-01T21:54:09Z", "canceled": false, "nbbo_ask": "198.32", "nbbo_bid": "198.24", "ext_hour_sold_codes": "extended_hours_trade", "market_center": "L", "nbbo_ask_quantity": 11, "nbbo_bid_quantity": 211, "tracking_id": 30575951029290, "trade_code": null, "trade_settlement": "regular", "trf_executed_at": "2026-05-01T21:54:09Z"}, {"size": 2000, "ticker": "EBAY", "price": "118.7", "sale_cond_codes": null, "premium": "237400.0", "volume": 11498274, "executed_at": "2026-05-01T21:54:08Z", "canceled": false, "nbbo_ask": "119.43", "nbbo_bid": "118.96", "ext_hour_sold_codes": "extended_hours_trade", "market_center": "L", "nbbo_ask_quantity": 116, "nbbo_bid_quantity": 1, "tracking_id": 30859418870623, "trade_code": null, "trade_settlement": "regular", "trf_executed_at": "2026-05-01T21:54:08Z"}, {"size": 3730, "ticker": "RBLX", "price": "45.16", "sale_cond_codes": null, "premium": "168446.80", "volume": 53323868, "executed_at": "2026-05-01T21:54:08Z", "canceled": false, "nbbo_ask": "45.2", "nbbo_bid": "45.16", "ext_hour_sold_codes": "extended_hours_trade", "market_center": "L", "nbbo_ask_quantity": 1292, "nbbo_bid_quantity": 20, "tracking_id": 23141362639691, "trade_code": null, "trade_settlement": "regular", "trf_executed_at": "2026-05-01T21:54:08Z"}, {"size": 2607, "ticker": "NVDA", "price": "198.3", "sale_cond_codes": null, "premium": "516968.1", "volume": 128207317, "executed_at": "2026-05-01T21:54:08Z", "canceled": false, "nbbo_ask": "198.32", "nbbo_bid": "198.24", "ext_hour_sold_codes": "extended_hours_trade", "market_center": "L", "nbbo_ask_quantity": 11, "nbbo_bid_quantity": 211, "tracking_id": 30575951028474, "trade_code": null, "trade_settlement": "regular", "trf_executed_at": "2026-05-01T21:54:08Z"}, {"size": 2000, "ticker": "EBAY", "price": "118.7", "sale_cond_codes": null, "premium": "237400.0", "volume": 11494116, "executed_at": "2026-05-01T21:54:01Z", "canceled": false, "nbbo_ask": "119.25", "nbbo_bid": "118.7", "ext_hour_sold_codes": "extended_hours_trade", "market_center": "L", "nbbo_ask_quantity": 100, "nbbo_bid_quantity": 100, "tracking_id": 30859418862803, "trade_code": null, "trade_settlement": "regular", "trf_executed_at": "2026-05-01T21:54:01Z"}, {"size": 201, "ticker": "MU", "price": "540.02", "sale_cond_codes": null, "premium": "108544.02", "volume": 40104845, "executed_at": "2026-05-01T21:54:00Z", "canceled": false, "nbbo_ask": "540.45", "nbbo_bid": "540.35", "ext_hour_sold_codes": "extended_hours_trade", "market_center": "L", "nbbo_ask_quantity": 167, "nbbo_bid_quantity": 2, "tracking_id": 27389085287077, "trade_code": null, "trade_settlement": "regular", "trf_executed_at": "2026-05-01T21:54:00Z"}, {"size": 979, "ticker": "SPY", "price": "720.1905", "sale_cond_codes": null, "premium": "705066.4995", "volume": 42681473, "executed_at": "2026-05-01T21:53:59Z", "canceled": false, "nbbo_ask": "720.24", "nbbo_bid": "719.8", "ext_hour_sold_codes": "extended_hours_trade", "market_center": "L", "nbbo_ask_quantity": 300, "nbbo_bid_quantity": 5, "tracking_id": 10509863813100, "trade_code": null, "trade_settlement": "regular", "trf_executed_at": "2026-05-01T21:53:59Z"}, {"size": 300, "ticker": "GOOGL", "price": "385.2175", "sale_cond_codes": null, "premium": "115565.2500", "volume": 30066834, "executed_at": "2026-05-01T21:53:57Z", "canceled": false, "nbbo_ask": "385.25", "nbbo_bid": "385.2", "ext_hour_sold_codes": "extended_hours_trade", "market_center": "L", "nbbo_ask_quantity": 52, "nbbo_bid_quantity": 5, "tracking_id": 32238103361548, "trade_code": null, "trade_settlement": "regular", "trf_executed_at": "2026-05-01T21:53:57Z"}, {"size": 300, "ticker": "GOOGL", "price": "385.2175", "sale_cond_codes": null, "premium": "115565.2500", "volume": 30066514, "executed_at": "2026-05-01T21:53:53Z", "canceled": false, "nbbo_ask": "385.25", "nbbo_bid": "385.2", "ext_hour_sold_codes": "extended_hours_trade", "market_center": "L", "nbbo_ask_quantity": 60, "nbbo_bid_quantity": 5, "tracking_id": 32238103356897, "trade_code": null, "trade_settlement": "regular", "trf_executed_at": "2026-05-01T21:53:53Z"}, {"size": 400, "ticker": "MU", "price": "540.02", "sale_cond_codes": null, "premium": "216008.00", "volume": 40104608, "executed_at": "2026-05-01T21:53:50Z", "canceled": false, "nbbo_ask": "540.45", "nbbo_bid": "540.02", "ext_hour_sold_codes": "extended_hours_trade", "market_center": "L", "nbbo_ask_quantity": 167, "nbbo_bid_quantity": 31, "tracking_id": 27389085277076, "trade_code": null, "trade_settlement": "regular", "trf_executed_at": "2026-05-01T21:53:50Z"}, {"size": 8500, "ticker": "BOXX", "price": "116.58", "sale_cond_codes": null, "premium": "990930.00", "volume": 2068790, "executed_at": "2026-05-01T21:53:43Z", "canceled": false, "nbbo_ask": "116.6", "nbbo_bid": "116.56", "ext_hour_sold_codes": "extended_hours_trade", "market_center": "L", "nbbo_ask_quantity": 927, "nbbo_bid_quantity": 291, "tracking_id": 6622918394108, "trade_code": null, "trade_settlement": "regular", "trf_executed_at": "2026-05-01T21:53:43Z"}, {"size": 8500, "ticker": "BOXX", "price": "116.5799", "sale_cond_codes": null, "premium": "990929.1500", "volume": 2060290, "executed_at": "2026-05-01T21:53:43Z", "canceled": false, "nbbo_ask": "116.6", "nbbo_bid": "116.56", "ext_hour_sold_codes": "extended_hours_trade", "market_center": "L", "nbbo_ask_quantity": 927, "nbbo_bid_quantity": 291, "tracking_id": 6622918394104, "trade_code": null, "trade_settlement": "regular", "trf_executed_at": "2026-05-01T21:53:43Z"}, {"size": 199, "ticker": "QQQ", "price": "673.93", "sale_cond_codes": null, "premium": "134112.07", "volume": 39011465, "executed_at": "2026-05-01T21:53:34Z", "canceled": false, "nbbo_ask": "673.93", "nbbo_bid": "673.9", "ext_hour_sold_codes": "extended_hours_trade", "market_center": "L", "nbbo_ask_quantity": 25, "nbbo_bid_quantity": 77, "tracking_id": 10501273853610, "trade_code": null, "trade_settlement": "regular", "trf_executed_at": "2026-05-01T21:53:34Z"}, {"size": 961, "ticker": "EBAY", "price": "119.44", "sale_cond_codes": null, "premium": "114781.84", "volume": 11489168, "executed_at": "2026-05-01T21:53:34Z", "canceled": false, "nbbo_ask": "119.43", "nbbo_bid": "119.01", "ext_hour_sold_codes": "extended_hours_trade", "market_center": "L", "nbbo_ask_quantity": 126, "nbbo_bid_quantity": 100, "tracking_id": 30859418836355, "trade_code": null, "trade_settlement": "regular", "trf_executed_at": "2026-05-01T21:53:34Z"}, {"size": 2000, "ticker": "EBAY", "price": "118.56", "sale_cond_codes": null, "premium": "237120.00", "volume": 11488038, "executed_at": "2026-05-01T21:53:32Z", "canceled": false, "nbbo_ask": "119.56", "nbbo_bid": "118.1", "ext_hour_sold_codes": "extended_hours_trade", "market_center": "L", "nbbo_ask_quantity": 10, "nbbo_bid_quantity": 500, "tracking_id": 30859418834673, "trade_code": null, "trade_settlement": "regular", "trf_executed_at": "2026-05-01T21:53:32Z"}, {"size": 200, "ticker": "MU", "price": "540.02", "sale_cond_codes": null, "premium": "108004.00", "volume": 40103387, "executed_at": "2026-05-01T21:53:20Z", "canceled": false, "nbbo_ask": "540.45", "nbbo_bid": "540.4", "ext_hour_sold_codes": "extended_hours_trade", "market_center": "L", "nbbo_ask_quantity": 167, "nbbo_bid_quantity": 1, "tracking_id": 27389085247076, "trade_code": null, "trade_settlement": "regular", "trf_executed_at": "2026-05-01T21:53:20Z"}, {"size": 5000, "ticker": "GME", "price": "27.65", "sale_cond_codes": null, "premium": "138250.00", "volume": 18038038, "executed_at": "2026-05-01T21:53:14Z", "canceled": false, "nbbo_ask": "27.7", "nbbo_bid": "27.65", "ext_hour_sold_codes": "extended_hours_trade", "market_center": "L", "nbbo_ask_quantity": 50, "nbbo_bid_quantity": 308, "tracking_id": 32504391290547, "trade_code": null, "trade_settlement": "regular", "trf_executed_at": "2026-05-01T21:53:14Z"}, {"size": 2000, "ticker": "EBAY", "price": "118.5", "sale_cond_codes": null, "premium": "237000.0", "volume": 11477860, "executed_at": "2026-05-01T21:53:14Z", "canceled": false, "nbbo_ask": "119.09", "nbbo_bid": "118.1", "ext_hour_sold_codes": "extended_hours_trade", "market_center": "L", "nbbo_ask_quantity": 250, "nbbo_bid_quantity": 500, "tracking_id": 30859418816133, "trade_code": null, "trade_settlement": "regular", "trf_executed_at": "2026-05-01T21:53:14Z"}, {"size": 2000, "ticker": "EBAY", "price": "118.7", "sale_cond_codes": null, "premium": "237400.0", "volume": 11474839, "executed_at": "2026-05-01T21:53:09Z", "canceled": false, "nbbo_ask": "119.09", "nbbo_bid": "118.1", "ext_hour_sold_codes": "extended_hours_trade", "market_center": "L", "nbbo_ask_quantity": 300, "nbbo_bid_quantity": 500, "tracking_id": 30859418811299, "trade_code": null, "trade_settlement": "regular", "trf_executed_at": "2026-05-01T21:53:09Z"}, {"size": 1217, "ticker": "INTC", "price": "99.9", "sale_cond_codes": null, "premium": "121578.3", "volume": 157298895, "executed_at": "2026-05-01T21:53:04Z", "canceled": false, "nbbo_ask": "99.9", "nbbo_bid": "99.85", "ext_hour_sold_codes": "extended_hours_trade", "market_center": "L", "nbbo_ask_quantity": 135, "nbbo_bid_quantity": 4163, "tracking_id": 25812832233495, "trade_code": null, "trade_settlement": "regular", "trf_executed_at": "2026-05-01T21:53:04Z"}, {"size": 2000, "ticker": "EBAY", "price": "118.5", "sale_cond_codes": null, "premium": "237000.0", "volume": 11469777, "executed_at": "2026-05-01T21:53:01Z", "canceled": false, "nbbo_ask": "119.88", "nbbo_bid": "118.1", "ext_hour_sold_codes": "extended_hours_trade", "market_center": "L", "nbbo_ask_quantity": 1000, "nbbo_bid_quantity": 500, "tracking_id": 30859418803121, "trade_code": null, "trade_settlement": "regular", "trf_executed_at": "2026-05-01T21:53:01Z"}, {"size": 1600, "ticker": "EBAY", "price": "118.78", "sale_cond_codes": null, "premium": "190048.00", "volume": 11450809, "executed_at": "2026-05-01T21:52:57Z", "canceled": false, "nbbo_ask": "118.8", "nbbo_bid": "118.55", "ext_hour_sold_codes": "extended_hours_trade", "market_center": "L", "nbbo_ask_quantity": 110, "nbbo_bid_quantity": 100, "tracking_id": 30859418799100, "trade_code": null, "trade_settlement": "regular", "trf_executed_at": "2026-05-01T21:52:57Z"}, {"size": 2000, "ticker": "EBAY", "price": "118.17", "sale_cond_codes": null, "premium": "236340.00", "volume": 11445437, "executed_at": "2026-05-01T21:52:52Z", "canceled": false, "nbbo_ask": "118.6", "nbbo_bid": "118.1", "ext_hour_sold_codes": "extended_hours_trade", "market_center": "L", "nbbo_ask_quantity": 2, "nbbo_bid_quantity": 500, "tracking_id": 30859418793889, "trade_code": null, "trade_settlement": "regular", "trf_executed_at": "2026-05-01T21:52:52Z"}, {"size": 3000, "ticker": "INTC", "price": "99.9", "sale_cond_codes": null, "premium": "299700.0", "volume": 157292727, "executed_at": "2026-05-01T21:52:49Z", "canceled": false, "nbbo_ask": "99.92", "nbbo_bid": "99.89", "ext_hour_sold_codes": "extended_hours_trade", "market_center": "L", "nbbo_ask_quantity": 117, "nbbo_bid_quantity": 98, "tracking_id": 25812832218844, "trade_code": null, "trade_settlement": "regular", "trf_executed_at": "2026-05-01T21:52:49Z"}, {"size": 500, "ticker": "GOOGL", "price": "385.13", "sale_cond_codes": null, "premium": "192565.00", "volume": 30066166, "executed_at": "2026-05-01T21:52:48Z", "canceled": false, "nbbo_ask": "385.26", "nbbo_bid": "385.02", "ext_hour_sold_codes": "extended_hours_trade", "market_center": "L", "nbbo_ask_quantity": 63, "nbbo_bid_quantity": 20, "tracking_id": 32238103292408, "trade_code": null, "trade_settlement": "regular", "trf_executed_at": "2026-05-01T21:52:48Z"}, {"size": 2000, "ticker": "EBAY", "price": "118.1", "sale_cond_codes": null, "premium": "236200.0", "volume": 11440499, "executed_at": "2026-05-01T21:52:45Z", "canceled": false, "nbbo_ask": "118.5", "nbbo_bid": "118.1", "ext_hour_sold_codes": "extended_hours_trade", "market_center": "L", "nbbo_ask_quantity": 5, "nbbo_bid_quantity": 500, "tracking_id": 30859418787373, "trade_code": null, "trade_settlement": "regular", "trf_executed_at": "2026-05-01T21:52:45Z"}, {"size": 450, "ticker": "QQQ", "price": "673.8", "sale_cond_codes": null, "premium": "303210.0", "volume": 39007381, "executed_at": "2026-05-01T21:52:34Z", "canceled": false, "nbbo_ask": "673.82", "nbbo_bid": "673.7", "ext_hour_sold_codes": "extended_hours_trade", "market_center": "L", "nbbo_ask_quantity": 20, "nbbo_bid_quantity": 500, "tracking_id": 10501273793282, "trade_code": null, "trade_settlement": "regular", "trf_executed_at": "2026-05-01T21:52:34Z"}, {"size": 47200, "ticker": "XXRP", "price": "4.01", "sale_cond_codes": null, "premium": "189272.00", "volume": 1422191, "executed_at": "2026-05-01T21:52:12Z", "canceled": false, "nbbo_ask": "4.04", "nbbo_bid": "4", "ext_hour_sold_codes": "extended_hours_trade", "market_center": "L", "nbbo_ask_quantity": 146, "nbbo_bid_quantity": 23, "tracking_id": 124632783978, "trade_code": null, "trade_settlement": "regular", "trf_executed_at": "2026-05-01T21:52:12Z"}, {"size": 1000, "ticker": "SOXL", "price": "129.86", "sale_cond_codes": null, "premium": "129860.00", "volume": 40644611, "executed_at": "2026-05-01T21:52:10Z", "canceled": false, "nbbo_ask": "129.88", "nbbo_bid": "129.86", "ext_hour_sold_codes": "extended_hours_trade", "market_center": "L", "nbbo_ask_quantity": 74, "nbbo_bid_quantity": 1, "tracking_id": 12760426567333, "trade_code": null, "trade_settlement": "regular", "trf_executed_at": "2026-05-01T21:52:10Z"}, {"size": 1200, "ticker": "INTC", "price": "99.88", "sale_cond_codes": null, "premium": "119856.00", "volume": 157287078, "executed_at": "2026-05-01T21:51:59Z", "canceled": false, "nbbo_ask": "99.9", "nbbo_bid": "99.88", "ext_hour_sold_codes": "extended_hours_trade", "market_center": "L", "nbbo_ask_quantity": 4, "nbbo_bid_quantity": 482, "tracking_id": 25812832168080, "trade_code": null, "trade_settlement": "regular", "trf_executed_at": "2026-05-01T21:51:59Z"}, {"size": 1000, "ticker": "GOOG", "price": "382.65", "sale_cond_codes": null, "premium": "382650.00", "volume": 28002624, "executed_at": "2026-05-01T21:51:57Z", "canceled": false, "nbbo_ask": "382.75", "nbbo_bid": "382.57", "ext_hour_sold_codes": "extended_hours_trade", "market_center": "L", "nbbo_ask_quantity": 50, "nbbo_bid_quantity": 1, "tracking_id": 43297644028798, "trade_code": null, "trade_settlement": "regular", "trf_executed_at": "2026-05-01T21:51:57Z"}, {"size": 200, "ticker": "MU", "price": "540.02", "sale_cond_codes": null, "premium": "108004.00", "volume": 40102995, "executed_at": "2026-05-01T21:51:45Z", "canceled": false, "nbbo_ask": "540.45", "nbbo_bid": "540.02", "ext_hour_sold_codes": "extended_hours_trade", "market_center": "L", "nbbo_ask_quantity": 217, "nbbo_bid_quantity": 100, "tracking_id": 27389085151886, "trade_code": null, "trade_settlement": "regular", "trf_executed_at": "2026-05-01T21:51:45Z"}, {"size": 1133, "ticker": "EBAY", "price": "118.15", "sale_cond_codes": null, "premium": "133863.95", "volume": 11426401, "executed_at": "2026-05-01T21:51:44Z", "canceled": false, "nbbo_ask": "118.3", "nbbo_bid": "118", "ext_hour_sold_codes": "extended_hours_trade", "market_center": "L", "nbbo_ask_quantity": 382, "nbbo_bid_quantity": 17, "tracking_id": 30859418725854, "trade_code": null, "trade_settlement": "regular", "trf_executed_at": "2026-05-01T21:51:44Z"}, {"size": 5012, "ticker": "GME", "price": "27.69", "sale_cond_codes": null, "premium": "138782.28", "volume": 18004690, "executed_at": "2026-05-01T21:51:43Z", "canceled": false, "nbbo_ask": "27.74", "nbbo_bid": "27.69", "ext_hour_sold_codes": "extended_hours_trade", "market_center": "L", "nbbo_ask_quantity": 323, "nbbo_bid_quantity": 1000, "tracking_id": 32504391199154, "trade_code": null, "trade_settlement": "regular", "trf_executed_at": "2026-05-01T21:51:43Z"}, {"size": 400, "ticker": "MU", "price": "540.2", "sale_cond_codes": null, "premium": "216080.0", "volume": 40102312, "executed_at": "2026-05-01T21:51:25Z", "canceled": false, "nbbo_ask": "540.45", "nbbo_bid": "540.2", "ext_hour_sold_codes": "extended_hours_trade", "market_center": "L", "nbbo_ask_quantity": 217, "nbbo_bid_quantity": 100, "tracking_id": 27389085131885, "trade_code": null, "trade_settlement": "regular", "trf_executed_at": "2026-05-01T21:51:25Z"}, {"size": 1800, "ticker": "KO", "price": "78.64", "sale_cond_codes": null, "premium": "141552.00", "volume": 12608019, "executed_at": "2026-05-01T21:51:24Z", "canceled": false, "nbbo_ask": "78.8", "nbbo_bid": "78.59", "ext_hour_sold_codes": "extended_hours_trade", "market_center": "L", "nbbo_ask_quantity": 400, "nbbo_bid_quantity": 100, "tracking_id": 25336090764061, "trade_code": null, "trade_settlement": "regular", "trf_executed_at": "2026-05-01T21:51:24Z"}, {"size": 140, "ticker": "STX", "price": "728.3", "sale_cond_codes": null, "premium": "101962.0", "volume": 7363659, "executed_at": "2026-05-01T21:51:17Z", "canceled": false, "nbbo_ask": "728.3", "nbbo_bid": "727.5", "ext_hour_sold_codes": "extended_hours_trade", "market_center": "L", "nbbo_ask_quantity": 2, "nbbo_bid_quantity": 12, "tracking_id": 31602448041559, "trade_code": null, "trade_settlement": "regular", "trf_executed_at": "2026-05-01T21:51:17Z"}, {"size": 1767, "ticker": "HOOD", "price": "73.45", "sale_cond_codes": null, "premium": "129786.15", "volume": 25178027, "executed_at": "2026-05-01T21:51:17Z", "canceled": false, "nbbo_ask": "73.5", "nbbo_bid": "73.44", "ext_hour_sold_codes": "extended_hours_trade", "market_center": "L", "nbbo_ask_quantity": 80, "nbbo_bid_quantity": 5, "tracking_id": 22123455219225, "trade_code": null, "trade_settlement": "regular", "trf_executed_at": "2026-05-01T21:51:17Z"}, {"size": 360, "ticker": "TSLA", "price": "391.7", "sale_cond_codes": null, "premium": "141012.0", "volume": 65186290, "executed_at": "2026-05-01T21:51:17Z", "canceled": false, "nbbo_ask": "391.75", "nbbo_bid": "391.65", "ext_hour_sold_codes": "extended_hours_trade", "market_center": "L", "nbbo_ask_quantity": 100, "nbbo_bid_quantity": 80, "tracking_id": 32431376729124, "trade_code": null, "trade_settlement": "regular", "trf_executed_at": "2026-05-01T21:51:17Z"}, {"size": 212, "ticker": "MU", "price": "540.2", "sale_cond_codes": null, "premium": "114522.4", "volume": 40101778, "executed_at": "2026-05-01T21:51:15Z", "canceled": false, "nbbo_ask": "540.45", "nbbo_bid": "540.4", "ext_hour_sold_codes": "extended_hours_trade", "market_center": "L", "nbbo_ask_quantity": 217, "nbbo_bid_quantity": 5, "tracking_id": 27389085121886, "trade_code": null, "trade_settlement": "regular", "trf_executed_at": "2026-05-01T21:51:15Z"}, {"size": 1000, "ticker": "NVDA", "price": "198.2174", "sale_cond_codes": null, "premium": "198217.4000", "volume": 128199204, "executed_at": "2026-05-01T21:51:10Z", "canceled": false, "nbbo_ask": "198.22", "nbbo_bid": "198.2", "ext_hour_sold_codes": "extended_hours_trade", "market_center": "L", "nbbo_ask_quantity": 88, "nbbo_bid_quantity": 5159, "tracking_id": 30575950850910, "trade_code": null, "trade_settlement": "regular", "trf_executed_at": "2026-05-01T21:51:10Z"}, {"size": 778, "ticker": "AAOI", "price": "182.12", "sale_cond_codes": null, "premium": "141689.36", "volume": 13166678, "executed_at": "2026-05-01T21:51:05Z", "canceled": false, "nbbo_ask": "182.2", "nbbo_bid": "181.5", "ext_hour_sold_codes": "extended_hours_trade", "market_center": "L", "nbbo_ask_quantity": 100, "nbbo_bid_quantity": 84, "tracking_id": 31709822211396, "trade_code": null, "trade_settlement": "regular", "trf_executed_at": "2026-05-01T21:51:05Z"}, {"size": 3000, "ticker": "CSCO", "price": "91.5812", "sale_cond_codes": null, "premium": "274743.6000", "volume": 16085034, "executed_at": "2026-05-01T21:51:05Z", "canceled": false, "nbbo_ask": "91.7", "nbbo_bid": "91.58", "ext_hour_sold_codes": "extended_hours_trade", "market_center": "L", "nbbo_ask_quantity": 699, "nbbo_bid_quantity": 3000, "tracking_id": 28544431314239, "trade_code": null, "trade_settlement": "regular", "trf_executed_at": "2026-05-01T21:51:05Z"}, {"size": 1428, "ticker": "NVDA", "price": "198.21", "sale_cond_codes": null, "premium": "283043.88", "volume": 128198057, "executed_at": "2026-05-01T21:51:01Z", "canceled": false, "nbbo_ask": "198.22", "nbbo_bid": "198.2", "ext_hour_sold_codes": "extended_hours_trade", "market_center": "L", "nbbo_ask_quantity": 15, "nbbo_bid_quantity": 5160, "tracking_id": 30575950841585, "trade_code": null, "trade_settlement": "regular", "trf_executed_at": "2026-05-01T21:51:01Z"}, {"size": 177, "ticker": "META", "price": "608.55", "sale_cond_codes": null, "premium": "107713.35", "volume": 21336518, "executed_at": "2026-05-01T21:50:56Z", "canceled": false, "nbbo_ask": "608.61", "nbbo_bid": "608.51", "ext_hour_sold_codes": "extended_hours_trade", "market_center": "L", "nbbo_ask_quantity": 8, "nbbo_bid_quantity": 50, "tracking_id": 32508686120026, "trade_code": null, "trade_settlement": "regular", "trf_executed_at": "2026-05-01T21:50:56Z"}, {"size": 160, "ticker": "QQQ", "price": "673.825", "sale_cond_codes": null, "premium": "107812.000", "volume": 39005953, "executed_at": "2026-05-01T21:50:46Z", "canceled": false, "nbbo_ask": "673.85", "nbbo_bid": "673.82", "ext_hour_sold_codes": "extended_hours_trade", "market_center": "L", "nbbo_ask_quantity": 1, "nbbo_bid_quantity": 78, "tracking_id": 10501273685636, "trade_code": null, "trade_settlement": "regular", "trf_executed_at": "2026-05-01T21:50:46Z"}, {"size": 3700, "ticker": "EBAY", "price": "118.4", "sale_cond_codes": null, "premium": "438080.0", "volume": 11408298, "executed_at": "2026-05-01T21:50:42Z", "canceled": false, "nbbo_ask": "118.38", "nbbo_bid": "117.53", "ext_hour_sold_codes": "extended_hours_trade", "market_center": "L", "nbbo_ask_quantity": 755, "nbbo_bid_quantity": 10, "tracking_id": 30859418664242, "trade_code": null, "trade_settlement": "regular", "trf_executed_at": "2026-05-01T21:50:42Z"}, {"size": 10000, "ticker": "EBAY", "price": "118.88", "sale_cond_codes": null, "premium": "1188800.00", "volume": 11402577, "executed_at": "2026-05-01T21:50:35Z", "canceled": false, "nbbo_ask": "118.57", "nbbo_bid": "117", "ext_hour_sold_codes": "extended_hours_trade", "market_center": "L", "nbbo_ask_quantity": 300, "nbbo_bid_quantity": 500, "tracking_id": 30859418657485, "trade_code": null, "trade_settlement": "regular", "trf_executed_at": "2026-05-01T21:50:35Z"}, {"size": 851, "ticker": "ABBV", "price": "206.59", "sale_cond_codes": null, "premium": "175808.09", "volume": 6340394, "executed_at": "2026-05-01T21:50:29Z", "canceled": false, "nbbo_ask": "207.05", "nbbo_bid": "205.99", "ext_hour_sold_codes": "extended_hours_trade", "market_center": "L", "nbbo_ask_quantity": 5, "nbbo_bid_quantity": 2, "tracking_id": 34123593795968, "trade_code": null, "trade_settlement": "regular", "trf_executed_at": "2026-05-01T21:50:29Z"}, {"size": 200, "ticker": "META", "price": "608.549", "sale_cond_codes": null, "premium": "121709.800", "volume": 21336223, "executed_at": "2026-05-01T21:50:27Z", "canceled": false, "nbbo_ask": "608.61", "nbbo_bid": "608.51", "ext_hour_sold_codes": "extended_hours_trade", "market_center": "L", "nbbo_ask_quantity": 7, "nbbo_bid_quantity": 50, "tracking_id": 32508686091068, "trade_code": null, "trade_settlement": "regular", "trf_executed_at": "2026-05-01T21:50:27Z"}, {"size": 9200, "ticker": "SOXS", "price": "13.01", "sale_cond_codes": null, "premium": "119692.00", "volume": 123401619, "executed_at": "2026-05-01T21:50:26Z", "canceled": false, "nbbo_ask": "13.02", "nbbo_bid": "13.01", "ext_hour_sold_codes": "extended_hours_trade", "market_center": "L", "nbbo_ask_quantity": 69, "nbbo_bid_quantity": 154, "tracking_id": 12764721430559, "trade_code": null, "trade_settlement": "regular", "trf_executed_at": "2026-05-01T21:50:26Z"}, {"size": 11809, "ticker": "SOXS", "price": "13.01", "sale_cond_codes": null, "premium": "153635.09", "volume": 123392419, "executed_at": "2026-05-01T21:50:26Z", "canceled": false, "nbbo_ask": "13.02", "nbbo_bid": "13.01", "ext_hour_sold_codes": "extended_hours_trade", "market_center": "L", "nbbo_ask_quantity": 69, "nbbo_bid_quantity": 154, "tracking_id": 12764721430558, "trade_code": null, "trade_settlement": "regular", "trf_executed_at": "2026-05-01T21:50:26Z"}, {"size": 404, "ticker": "BE", "price": "292.6", "sale_cond_codes": null, "premium": "118210.4", "volume": 9511725, "executed_at": "2026-05-01T21:50:24Z", "canceled": false, "nbbo_ask": "292.92", "nbbo_bid": "292.3", "ext_hour_sold_codes": "extended_hours_trade", "market_center": "L", "nbbo_ask_quantity": 1, "nbbo_bid_quantity": 20, "tracking_id": 39264669644124, "trade_code": null, "trade_settlement": "regular", "trf_executed_at": "2026-05-01T21:50:24Z"}, {"size": 3500, "ticker": "AFRM", "price": "69.0815", "sale_cond_codes": "average_price_trade", "premium": "241785.2500", "volume": 6420691, "executed_at": "2026-05-01T21:50:21Z", "canceled": false, "nbbo_ask": "67.45", "nbbo_bid": "67", "ext_hour_sold_codes": "extended_hours_trade", "market_center": "L", "nbbo_ask_quantity": 1132, "nbbo_bid_quantity": 5, "tracking_id": 23600923912903, "trade_code": null, "trade_settlement": "regular", "trf_executed_at": "2026-05-01T21:50:21Z"}, {"size": 1035, "ticker": "EBAY", "price": "117", "sale_cond_codes": null, "premium": "121095", "volume": 11310121, "executed_at": "2026-05-01T21:50:21Z", "canceled": false, "nbbo_ask": "118.3", "nbbo_bid": "117.58", "ext_hour_sold_codes": "extended_hours_trade", "market_center": "L", "nbbo_ask_quantity": 154, "nbbo_bid_quantity": 100, "tracking_id": 30859418643050, "trade_code": null, "trade_settlement": "regular", "trf_executed_at": "2026-05-01T21:50:21Z"}, {"size": 5000, "ticker": "EBAY", "price": "117.7501", "sale_cond_codes": null, "premium": "588750.5000", "volume": 11279642, "executed_at": "2026-05-01T21:50:16Z", "canceled": false, "nbbo_ask": "117.93", "nbbo_bid": "117.67", "ext_hour_sold_codes": "extended_hours_trade", "market_center": "L", "nbbo_ask_quantity": 100, "nbbo_bid_quantity": 200, "tracking_id": 30859418638581, "trade_code": null, "trade_settlement": "regular", "trf_executed_at": "2026-05-01T21:50:16Z"}, {"size": 660, "ticker": "MU", "price": "540.11", "sale_cond_codes": null, "premium": "356472.60", "volume": 40100697, "executed_at": "2026-05-01T21:50:11Z", "canceled": false, "nbbo_ask": "540.19", "nbbo_bid": "540.11", "ext_hour_sold_codes": "extended_hours_trade", "market_center": "L", "nbbo_ask_quantity": 10, "nbbo_bid_quantity": 5, "tracking_id": 27389085058511, "trade_code": null, "trade_settlement": "regular", "trf_executed_at": "2026-05-01T21:50:11Z"}, {"size": 2250, "ticker": "EBAY", "price": "117.96", "sale_cond_codes": null, "premium": "265410.00", "volume": 11259940, "executed_at": "2026-05-01T21:50:08Z", "canceled": false, "nbbo_ask": "118.25", "nbbo_bid": "117.4", "ext_hour_sold_codes": "extended_hours_trade", "market_center": "L", "nbbo_ask_quantity": 5000, "nbbo_bid_quantity": 3, "tracking_id": 30859418629957, "trade_code": null, "trade_settlement": "regular", "trf_executed_at": "2026-05-01T21:50:08Z"}, {"size": 275, "ticker": "MSFT", "price": "412.83", "sale_cond_codes": null, "premium": "113528.25", "volume": 31319107, "executed_at": "2026-05-01T21:50:06Z", "canceled": false, "nbbo_ask": "412.88", "nbbo_bid": "412.86", "ext_hour_sold_codes": "extended_hours_trade", "market_center": "L", "nbbo_ask_quantity": 27, "nbbo_bid_quantity": 3, "tracking_id": 27895891194128, "trade_code": null, "trade_settlement": "regular", "trf_executed_at": "2026-05-01T21:50:06Z"}, {"size": 448, "ticker": "WDC", "price": "429.61", "sale_cond_codes": null, "premium": "192465.28", "volume": 15448848, "executed_at": "2026-05-01T21:50:00Z", "canceled": false, "nbbo_ask": "429.85", "nbbo_bid": "429.5", "ext_hour_sold_codes": "extended_hours_trade", "market_center": "L", "nbbo_ask_quantity": 9, "nbbo_bid_quantity": 5, "tracking_id": 26697595312276, "trade_code": null, "trade_settlement": "regular", "trf_executed_at": "2026-05-01T21:50:00Z"}, {"size": 6000, "ticker": "RIOT", "price": "18.3935", "sale_cond_codes": null, "premium": "110361.0000", "volume": 32887902, "executed_at": "2026-05-01T21:50:00Z", "canceled": false, "nbbo_ask": "18.4", "nbbo_bid": "18.33", "ext_hour_sold_codes": "extended_hours_trade", "market_center": "L", "nbbo_ask_quantity": 950, "nbbo_bid_quantity": 2000, "tracking_id": 31812901361534, "trade_code": null, "trade_settlement": "regular", "trf_executed_at": "2026-05-01T21:50:00Z"}, {"size": 800, "ticker": "AAOI", "price": "182", "sale_cond_codes": null, "premium": "145600", "volume": 13165668, "executed_at": "2026-05-01T21:49:56Z", "canceled": false, "nbbo_ask": "181.99", "nbbo_bid": "181.5", "ext_hour_sold_codes": "extended_hours_trade", "market_center": "L", "nbbo_ask_quantity": 19, "nbbo_bid_quantity": 84, "tracking_id": 31709822143265, "trade_code": null, "trade_settlement": "regular", "trf_executed_at": "2026-05-01T21:49:56Z"}, {"size": 275, "ticker": "MSFT", "price": "412.8735", "sale_cond_codes": null, "premium": "113540.2125", "volume": 31318708, "executed_at": "2026-05-01T21:49:50Z", "canceled": false, "nbbo_ask": "412.88", "nbbo_bid": "412.86", "ext_hour_sold_codes": "extended_hours_trade", "market_center": "L", "nbbo_ask_quantity": 40, "nbbo_bid_quantity": 3, "tracking_id": 27895891178001, "trade_code": null, "trade_settlement": "regular", "trf_executed_at": "2026-05-01T21:49:50Z"}, {"size": 1000, "ticker": "IWM", "price": "278.7", "sale_cond_codes": null, "premium": "278700.0", "volume": 28906285, "executed_at": "2026-05-01T21:49:49Z", "canceled": false, "nbbo_ask": "278.96", "nbbo_bid": "278.46", "ext_hour_sold_codes": "extended_hours_trade", "market_center": "L", "nbbo_ask_quantity": 300, "nbbo_bid_quantity": 300, "tracking_id": 11746814144403, "trade_code": null, "trade_settlement": "regular", "trf_executed_at": "2026-05-01T21:49:49Z"}, {"size": 4000, "ticker": "EBAY", "price": "117.52", "sale_cond_codes": null, "premium": "470080.00", "volume": 11242159, "executed_at": "2026-05-01T21:49:44Z", "canceled": false, "nbbo_ask": "118.34", "nbbo_bid": "117.4", "ext_hour_sold_codes": "extended_hours_trade", "market_center": "L", "nbbo_ask_quantity": 600, "nbbo_bid_quantity": 3, "tracking_id": 30859418606311, "trade_code": null, "trade_settlement": "regular", "trf_executed_at": "2026-05-01T21:49:44Z"}, {"size": 20200, "ticker": "SOXS", "price": "13.01", "sale_cond_codes": null, "premium": "262802.00", "volume": 123372099, "executed_at": "2026-05-01T21:49:40Z", "canceled": false, "nbbo_ask": "13.02", "nbbo_bid": "13", "ext_hour_sold_codes": "extended_hours_trade", "market_center": "L", "nbbo_ask_quantity": 69, "nbbo_bid_quantity": 103, "tracking_id": 12764721384053, "trade_code": null, "trade_settlement": "regular", "trf_executed_at": "2026-05-01T21:49:40Z"}, {"size": 240, "ticker": "LITE", "price": "951.8", "sale_cond_codes": null, "premium": "228432.0", "volume": 4754239, "executed_at": "2026-05-01T21:49:31Z", "canceled": false, "nbbo_ask": "952", "nbbo_bid": "951.75", "ext_hour_sold_codes": "extended_hours_trade", "market_center": "L", "nbbo_ask_quantity": 6, "nbbo_bid_quantity": 51, "tracking_id": 35523753077028, "trade_code": null, "trade_settlement": "regular", "trf_executed_at": "2026-05-01T21:49:31Z"}, {"size": 260, "ticker": "LITE", "price": "951.8", "sale_cond_codes": null, "premium": "247468.0", "volume": 4754499, "executed_at": "2026-05-01T21:49:31Z", "canceled": false, "nbbo_ask": "952", "nbbo_bid": "951.75", "ext_hour_sold_codes": "extended_hours_trade", "market_center": "L", "nbbo_ask_quantity": 6, "nbbo_bid_quantity": 51, "tracking_id": 35523753077028, "trade_code": null, "trade_settlement": "regular", "trf_executed_at": "2026-05-01T21:49:31Z"}, {"size": 61519, "ticker": "BBAI", "price": "4.12", "sale_cond_codes": null, "premium": "253458.28", "volume": 40560841, "executed_at": "2026-05-01T21:49:28Z", "canceled": false, "nbbo_ask": "4.13", "nbbo_bid": "4.12", "ext_hour_sold_codes": "extended_hours_trade", "market_center": "L", "nbbo_ask_quantity": 75296, "nbbo_bid_quantity": 160, "tracking_id": 23338930854899, "trade_code": null, "trade_settlement": "regular", "trf_executed_at": "2026-05-01T21:49:28Z"}, {"size": 400, "ticker": "QQQ", "price": "673.8", "sale_cond_codes": null, "premium": "269520.0", "volume": 39002381, "executed_at": "2026-05-01T21:49:24Z", "canceled": false, "nbbo_ask": "673.81", "nbbo_bid": "673.74", "ext_hour_sold_codes": "extended_hours_trade", "market_center": "L", "nbbo_ask_quantity": 2, "nbbo_bid_quantity": 1, "tracking_id": 10501273603528, "trade_code": null, "trade_settlement": "regular", "trf_executed_at": "2026-05-01T21:49:24Z"}, {"size": 8447, "ticker": "SPXU", "price": "41.9998", "sale_cond_codes": null, "premium": "354772.3106", "volume": 7741660, "executed_at": "2026-05-01T21:49:21Z", "canceled": false, "nbbo_ask": "42.03", "nbbo_bid": "41.91", "ext_hour_sold_codes": "extended_hours_trade", "market_center": "L", "nbbo_ask_quantity": 1012, "nbbo_bid_quantity": 10, "tracking_id": 12794786136017, "trade_code": null, "trade_settlement": "regular", "trf_executed_at": "2026-05-01T21:49:21Z"}, {"size": 565, "ticker": "COKE", "price": "203.7", "sale_cond_codes": null, "premium": "115090.5", "volume": 378649, "executed_at": "2026-05-01T21:49:20Z", "canceled": false, "nbbo_ask": "207.5", "nbbo_bid": "203.25", "ext_hour_sold_codes": "extended_hours_trade", "market_center": "L", "nbbo_ask_quantity": 25, "nbbo_bid_quantity": 15, "tracking_id": 26908048669555, "trade_code": null, "trade_settlement": "regular", "trf_executed_at": "2026-05-01T21:49:20Z"}, {"size": 594, "ticker": "NVDA", "price": "198.24", "sale_cond_codes": null, "premium": "117754.56", "volume": 128190794, "executed_at": "2026-05-01T21:49:15Z", "canceled": false, "nbbo_ask": "198.26", "nbbo_bid": "198.22", "ext_hour_sold_codes": "extended_hours_trade", "market_center": "L", "nbbo_ask_quantity": 2, "nbbo_bid_quantity": 148, "tracking_id": 30575950735602, "trade_code": null, "trade_settlement": "regular", "trf_executed_at": "2026-05-01T21:49:15Z"}, {"size": 2500, "ticker": "IREN", "price": "46.91", "sale_cond_codes": null, "premium": "117275.00", "volume": 25909482, "executed_at": "2026-05-01T21:49:12Z", "canceled": false, "nbbo_ask": "46.91", "nbbo_bid": "46.84", "ext_hour_sold_codes": "extended_hours_trade", "market_center": "L", "nbbo_ask_quantity": 15, "nbbo_bid_quantity": 230, "tracking_id": 21393310653572, "trade_code": null, "trade_settlement": "regular", "trf_executed_at": "2026-05-01T21:49:12Z"}, {"size": 750, "ticker": "NVDA", "price": "198.24", "sale_cond_codes": null, "premium": "148680.00", "volume": 128190198, "executed_at": "2026-05-01T21:49:09Z", "canceled": false, "nbbo_ask": "198.26", "nbbo_bid": "198.22", "ext_hour_sold_codes": "extended_hours_trade", "market_center": "L", "nbbo_ask_quantity": 2, "nbbo_bid_quantity": 148, "tracking_id": 30575950729568, "trade_code": null, "trade_settlement": "regular", "trf_executed_at": "2026-05-01T21:49:09Z"}, {"size": 1000, "ticker": "EBAY", "price": "118.1255", "sale_cond_codes": null, "premium": "118125.5000", "volume": 11216916, "executed_at": "2026-05-01T21:49:05Z", "canceled": false, "nbbo_ask": "118.34", "nbbo_bid": "117.98", "ext_hour_sold_codes": "extended_hours_trade", "market_center": "L", "nbbo_ask_quantity": 1400, "nbbo_bid_quantity": 1, "tracking_id": 30859418566989, "trade_code": null, "trade_settlement": "regular", "trf_executed_at": "2026-05-01T21:49:05Z"}, {"size": 1098, "ticker": "PLTR", "price": "144.1999", "sale_cond_codes": null, "premium": "158331.4902", "volume": 33074779, "executed_at": "2026-05-01T21:49:04Z", "canceled": false, "nbbo_ask": "144.2", "nbbo_bid": "144.06", "ext_hour_sold_codes": "extended_hours_trade", "market_center": "L", "nbbo_ask_quantity": 11, "nbbo_bid_quantity": 500, "tracking_id": 24249463898127, "trade_code": null, "trade_settlement": "regular", "trf_executed_at": "2026-05-01T21:49:04Z"}, {"size": 1098, "ticker": "PLTR", "price": "144.2", "sale_cond_codes": null, "premium": "158331.6", "volume": 33075877, "executed_at": "2026-05-01T21:49:04Z", "canceled": false, "nbbo_ask": "144.2", "nbbo_bid": "144.06", "ext_hour_sold_codes": "extended_hours_trade", "market_center": "L", "nbbo_ask_quantity": 11, "nbbo_bid_quantity": 500, "tracking_id": 24249463898127, "trade_code": null, "trade_settlement": "regular", "trf_executed_at": "2026-05-01T21:49:04Z"}, {"size": 1730, "ticker": "RKLB", "price": "79.2656", "sale_cond_codes": null, "premium": "137129.4880", "volume": 16301213, "executed_at": "2026-05-01T21:48:58Z", "canceled": false, "nbbo_ask": "79.36", "nbbo_bid": "79.25", "ext_hour_sold_codes": "extended_hours_trade", "market_center": "L", "nbbo_ask_quantity": 70, "nbbo_bid_quantity": 340, "tracking_id": 24253758858965, "trade_code": null, "trade_settlement": "regular", "trf_executed_at": "2026-05-01T21:48:58Z"}, {"size": 1228, "ticker": "NVDA", "price": "198.23", "sale_cond_codes": null, "premium": "243426.44", "volume": 128189199, "executed_at": "2026-05-01T21:48:55Z", "canceled": false, "nbbo_ask": "198.26", "nbbo_bid": "198.23", "ext_hour_sold_codes": "extended_hours_trade", "market_center": "L", "nbbo_ask_quantity": 2, "nbbo_bid_quantity": 1, "tracking_id": 30575950715809, "trade_code": null, "trade_settlement": "regular", "trf_executed_at": "2026-05-01T21:48:55Z"}, {"size": 12744, "ticker": "TSLL", "price": "13.13", "sale_cond_codes": null, "premium": "167328.72", "volume": 93685730, "executed_at": "2026-05-01T21:48:54Z", "canceled": false, "nbbo_ask": "13.13", "nbbo_bid": "13.11", "ext_hour_sold_codes": "extended_hours_trade", "market_center": "L", "nbbo_ask_quantity": 5157, "nbbo_bid_quantity": 460, "tracking_id": 7305817905028, "trade_code": null, "trade_settlement": "regular", "trf_executed_at": "2026-05-01T21:48:54Z"}, {"size": 260, "ticker": "QQQ", "price": "673.8001", "sale_cond_codes": null, "premium": "175188.0260", "volume": 39000376, "executed_at": "2026-05-01T21:48:50Z", "canceled": false, "nbbo_ask": "673.81", "nbbo_bid": "673.74", "ext_hour_sold_codes": "extended_hours_trade", "market_center": "L", "nbbo_ask_quantity": 2, "nbbo_bid_quantity": 1, "tracking_id": 10501273569639, "trade_code": null, "trade_settlement": "regular", "trf_executed_at": "2026-05-01T21:48:50Z"}, {"size": 62, "ticker": "MKL", "price": "1779.36", "sale_cond_codes": "prior_reference_price", "premium": "110320.32", "volume": 123805, "executed_at": "2026-05-01T21:48:49Z", "canceled": false, "nbbo_ask": "1830", "nbbo_bid": "1727.53", "ext_hour_sold_codes": "extended_hours_trade", "market_center": "L", "nbbo_ask_quantity": 1, "nbbo_bid_quantity": 1, "tracking_id": 31185836065679, "trade_code": null, "trade_settlement": "regular", "trf_executed_at": "2026-05-01T21:48:48Z"}, {"size": 622, "ticker": "RSP", "price": "202.82", "sale_cond_codes": "prior_reference_price", "premium": "126154.04", "volume": 13805718, "executed_at": "2026-05-01T21:48:49Z", "canceled": false, "nbbo_ask": "203.07", "nbbo_bid": "202.62", "ext_hour_sold_codes": "extended_hours_trade", "market_center": "L", "nbbo_ask_quantity": 99, "nbbo_bid_quantity": 4, "tracking_id": 13980197077903, "trade_code": null, "trade_settlement": "regular", "trf_executed_at": "2026-05-01T21:48:48Z"}, {"size": 3600, "ticker": "TQQQ", "price": "65.1", "sale_cond_codes": null, "premium": "234360.0", "volume": 67398646, "executed_at": "2026-05-01T21:48:44Z", "canceled": false, "nbbo_ask": "65.1", "nbbo_bid": "65.09", "ext_hour_sold_codes": "extended_hours_trade", "market_center": "L", "nbbo_ask_quantity": 23, "nbbo_bid_quantity": 547, "tracking_id": 12953699888739, "trade_code": null, "trade_settlement": "regular", "trf_executed_at": "2026-05-01T21:48:44Z"}, {"size": 1000, "ticker": "MU", "price": "540.1", "sale_cond_codes": null, "premium": "540100.0", "volume": 40099144, "executed_at": "2026-05-01T21:48:43Z", "canceled": false, "nbbo_ask": "540.09", "nbbo_bid": "540.01", "ext_hour_sold_codes": "extended_hours_trade", "market_center": "L", "nbbo_ask_quantity": 20, "nbbo_bid_quantity": 13, "tracking_id": 27389084970548, "trade_code": null, "trade_settlement": "regular", "trf_executed_at": "2026-05-01T21:48:43Z"}, {"size": 115, "ticker": "SNDK", "price": "1187.8", "sale_cond_codes": null, "premium": "136597.0", "volume": 22995218, "executed_at": "2026-05-01T21:48:41Z", "canceled": false, "nbbo_ask": "1188.3", "nbbo_bid": "1187.2", "ext_hour_sold_codes": "extended_hours_trade", "market_center": "L", "nbbo_ask_quantity": 20, "nbbo_bid_quantity": 50, "tracking_id": 18270869398836, "trade_code": null, "trade_settlement": "regular", "trf_executed_at": "2026-05-01T21:48:41Z"}, {"size": 500, "ticker": "SNDK", "price": "1187.25", "sale_cond_codes": null, "premium": "593625.00", "volume": 22995054, "executed_at": "2026-05-01T21:48:38Z", "canceled": false, "nbbo_ask": "1188.3", "nbbo_bid": "1187.2", "ext_hour_sold_codes": "extended_hours_trade", "market_center": "L", "nbbo_ask_quantity": 20, "nbbo_bid_quantity": 50, "tracking_id": 18270869395493, "trade_code": null, "trade_settlement": "regular", "trf_executed_at": "2026-05-01T21:48:38Z"}, {"size": 1700, "ticker": "INTC", "price": "99.8999", "sale_cond_codes": null, "premium": "169829.8300", "volume": 157272472, "executed_at": "2026-05-01T21:48:35Z", "canceled": false, "nbbo_ask": "99.9", "nbbo_bid": "99.86", "ext_hour_sold_codes": "extended_hours_trade", "market_center": "L", "nbbo_ask_quantity": 4, "nbbo_bid_quantity": 14, "tracking_id": 25812831964088, "trade_code": null, "trade_settlement": "regular", "trf_executed_at": "2026-05-01T21:48:35Z"}, {"size": 1700, "ticker": "INTC", "price": "99.9", "sale_cond_codes": null, "premium": "169830.0", "volume": 157270772, "executed_at": "2026-05-01T21:48:35Z", "canceled": false, "nbbo_ask": "99.9", "nbbo_bid": "99.86", "ext_hour_sold_codes": "extended_hours_trade", "market_center": "L", "nbbo_ask_quantity": 4, "nbbo_bid_quantity": 14, "tracking_id": 25812831964087, "trade_code": null, "trade_settlement": "regular", "trf_executed_at": "2026-05-01T21:48:35Z"}, {"size": 400, "ticker": "META", "price": "608.5", "sale_cond_codes": null, "premium": "243400.0", "volume": 21335472, "executed_at": "2026-05-01T21:48:30Z", "canceled": false, "nbbo_ask": "608.62", "nbbo_bid": "608.55", "ext_hour_sold_codes": "extended_hours_trade", "market_center": "L", "nbbo_ask_quantity": 5, "nbbo_bid_quantity": 5, "tracking_id": 32508685973933, "trade_code": null, "trade_settlement": "regular", "trf_executed_at": "2026-05-01T21:48:30Z"}, {"size": 64130, "ticker": "TZA", "price": "4.9", "sale_cond_codes": null, "premium": "314237.0", "volume": 107889667, "executed_at": "2026-05-01T21:48:21Z", "canceled": false, "nbbo_ask": "4.92", "nbbo_bid": "4.9", "ext_hour_sold_codes": "extended_hours_trade", "market_center": "L", "nbbo_ask_quantity": 1436, "nbbo_bid_quantity": 609, "tracking_id": 12979469670086, "trade_code": null, "trade_settlement": "regular", "trf_executed_at": "2026-05-01T21:48:21Z"}, {"size": 5392, "ticker": "GME", "price": "27.52", "sale_cond_codes": null, "premium": "148387.84", "volume": 17901925, "executed_at": "2026-05-01T21:48:18Z", "canceled": false, "nbbo_ask": "27.55", "nbbo_bid": "27.46", "ext_hour_sold_codes": "extended_hours_trade", "market_center": "L", "nbbo_ask_quantity": 235, "nbbo_bid_quantity": 62, "tracking_id": 32504390994429, "trade_code": null, "trade_settlement": "regular", "trf_executed_at": "2026-05-01T21:48:18Z"}, {"size": 1834, "ticker": "STRC", "price": "99.87", "sale_cond_codes": null, "premium": "183161.58", "volume": 2559167, "executed_at": "2026-05-01T21:48:15Z", "canceled": false, "nbbo_ask": "99.9", "nbbo_bid": "99.84", "ext_hour_sold_codes": "extended_hours_trade", "market_center": "L", "nbbo_ask_quantity": 400, "nbbo_bid_quantity": 24, "tracking_id": 63028723564002, "trade_code": null, "trade_settlement": "regular", "trf_executed_at": "2026-05-01T21:48:15Z"}, {"size": 525, "ticker": "BRKB", "price": "474.4", "sale_cond_codes": null, "premium": "249060.0", "volume": 4800984, "executed_at": "2026-05-01T21:48:14Z", "canceled": false, "nbbo_ask": "474.69", "nbbo_bid": "474.32", "ext_hour_sold_codes": "extended_hours_trade", "market_center": "L", "nbbo_ask_quantity": 5, "nbbo_bid_quantity": 234, "tracking_id": 44040673147204, "trade_code": null, "trade_settlement": "regular", "trf_executed_at": "2026-05-01T21:48:14Z"}, {"size": 4732, "ticker": "GME", "price": "27.52", "sale_cond_codes": null, "premium": "130224.64", "volume": 17894856, "executed_at": "2026-05-01T21:48:09Z", "canceled": false, "nbbo_ask": "27.59", "nbbo_bid": "27.45", "ext_hour_sold_codes": "extended_hours_trade", "market_center": "L", "nbbo_ask_quantity": 50, "nbbo_bid_quantity": 17, "tracking_id": 32504390986062, "trade_code": null, "trade_settlement": "regular", "trf_executed_at": "2026-05-01T21:48:09Z"}, {"size": 1055, "ticker": "TSLA", "price": "391.59", "sale_cond_codes": null, "premium": "413127.45", "volume": 65178349, "executed_at": "2026-05-01T21:48:02Z", "canceled": false, "nbbo_ask": "391.6", "nbbo_bid": "391.58", "ext_hour_sold_codes": "extended_hours_trade", "market_center": "L", "nbbo_ask_quantity": 5277, "nbbo_bid_quantity": 2, "tracking_id": 32431376534378, "trade_code": null, "trade_settlement": "regular", "trf_executed_at": "2026-05-01T21:48:02Z"}, {"size": 700, "ticker": "AAPL", "price": "279.99", "sale_cond_codes": null, "premium": "195993.00", "volume": 79832846, "executed_at": "2026-05-01T21:47:56Z", "canceled": false, "nbbo_ask": "279.99", "nbbo_bid": "279.93", "ext_hour_sold_codes": "extended_hours_trade", "market_center": "L", "nbbo_ask_quantity": 497, "nbbo_bid_quantity": 41, "tracking_id": 26946703291579, "trade_code": null, "trade_settlement": "regular", "trf_executed_at": "2026-05-01T21:47:56Z"}, {"size": 760, "ticker": "NVDA", "price": "198.2399", "sale_cond_codes": null, "premium": "150662.3240", "volume": 128183576, "executed_at": "2026-05-01T21:47:55Z", "canceled": false, "nbbo_ask": "198.26", "nbbo_bid": "198.23", "ext_hour_sold_codes": "extended_hours_trade", "market_center": "L", "nbbo_ask_quantity": 2, "nbbo_bid_quantity": 7, "tracking_id": 30575950655565, "trade_code": null, "trade_settlement": "regular", "trf_executed_at": "2026-05-01T21:47:55Z"}, {"size": 58354, "ticker": "SOXS", "price": "13", "sale_cond_codes": null, "premium": "758602", "volume": 123343917, "executed_at": "2026-05-01T21:47:54Z", "canceled": false, "nbbo_ask": "13.02", "nbbo_bid": "13.01", "ext_hour_sold_codes": "extended_hours_trade", "market_center": "L", "nbbo_ask_quantity": 76, "nbbo_bid_quantity": 244, "tracking_id": 12764721278654, "trade_code": null, "trade_settlement": "regular", "trf_executed_at": "2026-05-01T21:47:54Z"}, {"size": 11060, "ticker": "RDDT", "price": "167.9944", "sale_cond_codes": "average_price_trade", "premium": "1858018.0640", "volume": 14224304, "executed_at": "2026-05-01T21:47:54Z", "canceled": false, "nbbo_ask": "167.13", "nbbo_bid": "166.91", "ext_hour_sold_codes": "extended_hours_trade", "market_center": "L", "nbbo_ask_quantity": 200, "nbbo_bid_quantity": 500, "tracking_id": 19477755161497, "trade_code": null, "trade_settlement": "regular", "trf_executed_at": "2026-05-01T21:47:54Z"}, {"size": 495, "ticker": "MSFT", "price": "412.88", "sale_cond_codes": null, "premium": "204375.60", "volume": 31316758, "executed_at": "2026-05-01T21:47:54Z", "canceled": false, "nbbo_ask": "412.9", "nbbo_bid": "412.82", "ext_hour_sold_codes": "extended_hours_trade", "market_center": "L", "nbbo_ask_quantity": 6, "nbbo_bid_quantity": 5, "tracking_id": 27895891061593, "trade_code": null, "trade_settlement": "regular", "trf_executed_at": "2026-05-01T21:47:54Z"}, {"size": 9654, "ticker": "GME", "price": "27.59", "sale_cond_codes": null, "premium": "266353.86", "volume": 17885873, "executed_at": "2026-05-01T21:47:53Z", "canceled": false, "nbbo_ask": "27.6", "nbbo_bid": "27.4", "ext_hour_sold_codes": "extended_hours_trade", "market_center": "L", "nbbo_ask_quantity": 500, "nbbo_bid_quantity": 701, "tracking_id": 32504390969165, "trade_code": null, "trade_settlement": "regular", "trf_executed_at": "2026-05-01T21:47:53Z"}, {"size": 2000, "ticker": "INTC", "price": "99.8999", "sale_cond_codes": null, "premium": "199799.8000", "volume": 157267651, "executed_at": "2026-05-01T21:47:51Z", "canceled": false, "nbbo_ask": "99.92", "nbbo_bid": "99.87", "ext_hour_sold_codes": "extended_hours_trade", "market_center": "L", "nbbo_ask_quantity": 1, "nbbo_bid_quantity": 16, "tracking_id": 25812831920629, "trade_code": null, "trade_settlement": "regular", "trf_executed_at": "2026-05-01T21:47:51Z"}, {"size": 2000, "ticker": "INTC", "price": "99.9", "sale_cond_codes": null, "premium": "199800.0", "volume": 157265651, "executed_at": "2026-05-01T21:47:51Z", "canceled": false, "nbbo_ask": "99.92", "nbbo_bid": "99.87", "ext_hour_sold_codes": "extended_hours_trade", "market_center": "L", "nbbo_ask_quantity": 1, "nbbo_bid_quantity": 16, "tracking_id": 25812831920627, "trade_code": null, "trade_settlement": "regular", "trf_executed_at": "2026-05-01T21:47:51Z"}, {"size": 2320, "ticker": "TQQQ", "price": "65.1", "sale_cond_codes": null, "premium": "151032.0", "volume": 67394036, "executed_at": "2026-05-01T21:47:46Z", "canceled": false, "nbbo_ask": "65.1", "nbbo_bid": "65.07", "ext_hour_sold_codes": "extended_hours_trade", "market_center": "L", "nbbo_ask_quantity": 25, "nbbo_bid_quantity": 100, "tracking_id": 12953699831496, "trade_code": null, "trade_settlement": "regular", "trf_executed_at": "2026-05-01T21:47:46Z"}, {"size": 7748, "ticker": "GME", "price": "27.59", "sale_cond_codes": null, "premium": "213767.32", "volume": 17874324, "executed_at": "2026-05-01T21:47:46Z", "canceled": false, "nbbo_ask": "27.6", "nbbo_bid": "27.51", "ext_hour_sold_codes": "extended_hours_trade", "market_center": "L", "nbbo_ask_quantity": 500, "nbbo_bid_quantity": 3, "tracking_id": 32504390962842, "trade_code": null, "trade_settlement": "regular", "trf_executed_at": "2026-05-01T21:47:46Z"}, {"size": 450, "ticker": "SNDK", "price": "1188", "sale_cond_codes": null, "premium": "534600", "volume": 22993678, "executed_at": "2026-05-01T21:47:42Z", "canceled": false, "nbbo_ask": "1188.1", "nbbo_bid": "1187.2", "ext_hour_sold_codes": "extended_hours_trade", "market_center": "L", "nbbo_ask_quantity": 10, "nbbo_bid_quantity": 50, "tracking_id": 18270869339690, "trade_code": null, "trade_settlement": "regular", "trf_executed_at": "2026-05-01T21:47:42Z"}, {"size": 2000, "ticker": "EBAY", "price": "118", "sale_cond_codes": null, "premium": "236000", "volume": 11192321, "executed_at": "2026-05-01T21:47:22Z", "canceled": false, "nbbo_ask": "118.4", "nbbo_bid": "117.98", "ext_hour_sold_codes": "extended_hours_trade", "market_center": "L", "nbbo_ask_quantity": 369, "nbbo_bid_quantity": 1, "tracking_id": 30859418464379, "trade_code": null, "trade_settlement": "regular", "trf_executed_at": "2026-05-01T21:47:22Z"}, {"size": 605, "ticker": "AMD", "price": "360.73", "sale_cond_codes": null, "premium": "218241.65", "volume": 34144307, "executed_at": "2026-05-01T21:47:14Z", "canceled": false, "nbbo_ask": "360.74", "nbbo_bid": "360.7", "ext_hour_sold_codes": "extended_hours_trade", "market_center": "L", "nbbo_ask_quantity": 72, "nbbo_bid_quantity": 1, "tracking_id": 25005378031424, "trade_code": null, "trade_settlement": "regular", "trf_executed_at": "2026-05-01T21:47:14Z"}, {"size": 6100, "ticker": "BMNR", "price": "21.84", "sale_cond_codes": null, "premium": "133224.00", "volume": 29543193, "executed_at": "2026-05-01T21:47:08Z", "canceled": false, "nbbo_ask": "21.83", "nbbo_bid": "21.81", "ext_hour_sold_codes": "extended_hours_trade", "market_center": "L", "nbbo_ask_quantity": 94, "nbbo_bid_quantity": 10, "tracking_id": 70072469862541, "trade_code": null, "trade_settlement": "regular", "trf_executed_at": "2026-05-01T21:47:08Z"}, {"size": 326, "ticker": "LITE", "price": "951.99", "sale_cond_codes": null, "premium": "310348.74", "volume": 4753734, "executed_at": "2026-05-01T21:47:07Z", "canceled": false, "nbbo_ask": "952.89", "nbbo_bid": "951.75", "ext_hour_sold_codes": "extended_hours_trade", "market_center": "L", "nbbo_ask_quantity": 99, "nbbo_bid_quantity": 51, "tracking_id": 35523752932686, "trade_code": null, "trade_settlement": "regular", "trf_executed_at": "2026-05-01T21:47:07Z"}, {"size": 550, "ticker": "TLN", "price": "380", "sale_cond_codes": null, "premium": "209000", "volume": 573963, "executed_at": "2026-05-01T21:47:05Z", "canceled": false, "nbbo_ask": "384.34", "nbbo_bid": "371.35", "ext_hour_sold_codes": "extended_hours_trade", "market_center": "L", "nbbo_ask_quantity": 15, "nbbo_bid_quantity": 10, "tracking_id": 19134157729009, "trade_code": null, "trade_settlement": "regular", "trf_executed_at": "2026-05-01T21:47:05Z"}, {"size": 600, "ticker": "VTI", "price": "355.12", "sale_cond_codes": null, "premium": "213072.00", "volume": 3749510, "executed_at": "2026-05-01T21:46:58Z", "canceled": false, "nbbo_ask": "355.57", "nbbo_bid": "354.9", "ext_hour_sold_codes": "extended_hours_trade", "market_center": "L", "nbbo_ask_quantity": 99, "nbbo_bid_quantity": 1, "tracking_id": 13215692787825, "trade_code": null, "trade_settlement": "regular", "trf_executed_at": "2026-05-01T21:46:58Z"}, {"size": 640, "ticker": "VTI", "price": "355.12", "sale_cond_codes": null, "premium": "227276.80", "volume": 3748750, "executed_at": "2026-05-01T21:46:57Z", "canceled": false, "nbbo_ask": "355.57", "nbbo_bid": "354.9", "ext_hour_sold_codes": "extended_hours_trade", "market_center": "L", "nbbo_ask_quantity": 99, "nbbo_bid_quantity": 1, "tracking_id": 13215692787648, "trade_code": null, "trade_settlement": "regular", "trf_executed_at": "2026-05-01T21:46:57Z"}, {"size": 10784, "ticker": "SCHB", "price": "27.82", "sale_cond_codes": null, "premium": "300010.88", "volume": 7990408, "executed_at": "2026-05-01T21:46:57Z", "canceled": false, "nbbo_ask": "27.91", "nbbo_bid": "27.59", "ext_hour_sold_codes": "extended_hours_trade", "market_center": "L", "nbbo_ask_quantity": 6, "nbbo_bid_quantity": 3, "tracking_id": 12580037627130, "trade_code": null, "trade_settlement": "regular", "trf_executed_at": "2026-05-01T21:46:57Z"}, {"size": 999, "ticker": "CRCL", "price": "100.2103", "sale_cond_codes": null, "premium": "100110.0897", "volume": 9998932, "executed_at": "2026-05-01T21:46:51Z", "canceled": false, "nbbo_ask": "100.27", "nbbo_bid": "100.22", "ext_hour_sold_codes": "extended_hours_trade", "market_center": "L", "nbbo_ask_quantity": 100, "nbbo_bid_quantity": 66, "tracking_id": 70081059780273, "trade_code": null, "trade_settlement": "regular", "trf_executed_at": "2026-05-01T21:46:51Z"}, {"size": 29400, "ticker": "SOXS", "price": "13.03", "sale_cond_codes": null, "premium": "383082.00", "volume": 123273014, "executed_at": "2026-05-01T21:46:46Z", "canceled": false, "nbbo_ask": "13.03", "nbbo_bid": "13.02", "ext_hour_sold_codes": "extended_hours_trade", "market_center": "L", "nbbo_ask_quantity": 2665, "nbbo_bid_quantity": 600, "tracking_id": 12764721210417, "trade_code": null, "trade_settlement": "regular", "trf_executed_at": "2026-05-01T21:46:46Z"}, {"size": 16400, "ticker": "SOXS", "price": "13.03", "sale_cond_codes": null, "premium": "213692.00", "volume": 123243614, "executed_at": "2026-05-01T21:46:46Z", "canceled": false, "nbbo_ask": "13.03", "nbbo_bid": "13.02", "ext_hour_sold_codes": "extended_hours_trade", "market_center": "L", "nbbo_ask_quantity": 2665, "nbbo_bid_quantity": 600, "tracking_id": 12764721210415, "trade_code": null, "trade_settlement": "regular", "trf_executed_at": "2026-05-01T21:46:46Z"}, {"size": 1581, "ticker": "RKLB", "price": "79.25", "sale_cond_codes": null, "premium": "125294.25", "volume": 16299113, "executed_at": "2026-05-01T21:46:44Z", "canceled": false, "nbbo_ask": "79.37", "nbbo_bid": "79.27", "ext_hour_sold_codes": "extended_hours_trade", "market_center": "L", "nbbo_ask_quantity": 10, "nbbo_bid_quantity": 1, "tracking_id": 24253758725451, "trade_code": null, "trade_settlement": "regular", "trf_executed_at": "2026-05-01T21:46:44Z"}, {"size": 2000, "ticker": "OKLO", "price": "70.2", "sale_cond_codes": null, "premium": "140400.0", "volume": 10471188, "executed_at": "2026-05-01T21:46:44Z", "canceled": false, "nbbo_ask": "70.4", "nbbo_bid": "70.2", "ext_hour_sold_codes": "extended_hours_trade", "market_center": "L", "nbbo_ask_quantity": 24, "nbbo_bid_quantity": 2, "tracking_id": 22351088212549, "trade_code": null, "trade_settlement": "regular", "trf_executed_at": "2026-05-01T21:46:44Z"}, {"size": 1633, "ticker": "BOXX", "price": "116.58", "sale_cond_codes": null, "premium": "190375.14", "volume": 2049032, "executed_at": "2026-05-01T21:46:43Z", "canceled": false, "nbbo_ask": "116.6", "nbbo_bid": "116.56", "ext_hour_sold_codes": "extended_hours_trade", "market_center": "L", "nbbo_ask_quantity": 927, "nbbo_bid_quantity": 291, "tracking_id": 6622917973661, "trade_code": null, "trade_settlement": "regular", "trf_executed_at": "2026-05-01T21:46:43Z"}, {"size": 320, "ticker": "META", "price": "608.5", "sale_cond_codes": null, "premium": "194720.0", "volume": 21334538, "executed_at": "2026-05-01T21:46:42Z", "canceled": false, "nbbo_ask": "608.78", "nbbo_bid": "608.6", "ext_hour_sold_codes": "extended_hours_trade", "market_center": "L", "nbbo_ask_quantity": 2, "nbbo_bid_quantity": 92, "tracking_id": 32508685865904, "trade_code": null, "trade_settlement": "regular", "trf_executed_at": "2026-05-01T21:46:42Z"}, {"size": 2000, "ticker": "BIL", "price": "91.4001", "sale_cond_codes": null, "premium": "182800.2000", "volume": 14002897, "executed_at": "2026-05-01T21:46:26Z", "canceled": false, "nbbo_ask": "91.41", "nbbo_bid": "91.4", "ext_hour_sold_codes": "extended_hours_trade", "market_center": "L", "nbbo_ask_quantity": 24462, "nbbo_bid_quantity": 28614, "tracking_id": 10595762705706, "trade_code": null, "trade_settlement": "regular", "trf_executed_at": "2026-05-01T21:46:26Z"}, {"size": 2065, "ticker": "SGOV", "price": "100.41", "sale_cond_codes": null, "premium": "207346.65", "volume": 33424322, "executed_at": "2026-05-01T21:46:23Z", "canceled": false, "nbbo_ask": "100.42", "nbbo_bid": "100.41", "ext_hour_sold_codes": "extended_hours_trade", "market_center": "L", "nbbo_ask_quantity": 137, "nbbo_bid_quantity": 239963, "tracking_id": 10204920678721, "trade_code": null, "trade_settlement": "regular", "trf_executed_at": "2026-05-01T21:46:23Z"}, {"size": 4400, "ticker": "PULS", "price": "49.5899", "sale_cond_codes": null, "premium": "218195.5600", "volume": 2493662, "executed_at": "2026-05-01T21:46:07Z", "canceled": false, "nbbo_ask": "53.81", "nbbo_bid": "49.56", "ext_hour_sold_codes": "extended_hours_trade", "market_center": "L", "nbbo_ask_quantity": 100, "nbbo_bid_quantity": 4000, "tracking_id": 16613011868611, "trade_code": null, "trade_settlement": "regular", "trf_executed_at": "2026-05-01T21:46:07Z"}, {"size": 500, "ticker": "META", "price": "608.6199", "sale_cond_codes": null, "premium": "304309.9500", "volume": 21333586, "executed_at": "2026-05-01T21:46:02Z", "canceled": false, "nbbo_ask": "608.95", "nbbo_bid": "608.6", "ext_hour_sold_codes": "extended_hours_trade", "market_center": "L", "nbbo_ask_quantity": 35, "nbbo_bid_quantity": 95, "tracking_id": 32508685826210, "trade_code": null, "trade_settlement": "regular", "trf_executed_at": "2026-05-01T21:46:02Z"}, {"size": 11081, "ticker": "JOBY", "price": "9.25", "sale_cond_codes": null, "premium": "102499.25", "volume": 26698447, "executed_at": "2026-05-01T21:46:01Z", "canceled": false, "nbbo_ask": "9.27", "nbbo_bid": "9.25", "ext_hour_sold_codes": "extended_hours_trade", "market_center": "L", "nbbo_ask_quantity": 2, "nbbo_bid_quantity": 10, "tracking_id": 24343952995681, "trade_code": null, "trade_settlement": "regular", "trf_executed_at": "2026-05-01T21:46:01Z"}, {"size": 500, "ticker": "META", "price": "608.6", "sale_cond_codes": null, "premium": "304300.0", "volume": 21333074, "executed_at": "2026-05-01T21:45:52Z", "canceled": false, "nbbo_ask": "608.95", "nbbo_bid": "608.6", "ext_hour_sold_codes": "extended_hours_trade", "market_center": "L", "nbbo_ask_quantity": 35, "nbbo_bid_quantity": 95, "tracking_id": 32508685815769, "trade_code": null, "trade_settlement": "regular", "trf_executed_at": "2026-05-01T21:45:52Z"}, {"size": 240, "ticker": "AVGO", "price": "419.9095", "sale_cond_codes": null, "premium": "100778.2800", "volume": 11867854, "executed_at": "2026-05-01T21:45:40Z", "canceled": false, "nbbo_ask": "420.1", "nbbo_bid": "419.55", "ext_hour_sold_codes": "extended_hours_trade", "market_center": "L", "nbbo_ask_quantity": 497, "nbbo_bid_quantity": 66, "tracking_id": 33414923902904, "trade_code": null, "trade_settlement": "regular", "trf_executed_at": "2026-05-01T21:45:40Z"}, {"size": 300, "ticker": "SNDK", "price": "1188.25", "sale_cond_codes": null, "premium": "356475.00", "volume": 22991548, "executed_at": "2026-05-01T21:45:39Z", "canceled": false, "nbbo_ask": "1188.52", "nbbo_bid": "1188.03", "ext_hour_sold_codes": "extended_hours_trade", "market_center": "L", "nbbo_ask_quantity": 3, "nbbo_bid_quantity": 6, "tracking_id": 18270869216772, "trade_code": null, "trade_settlement": "regular", "trf_executed_at": "2026-05-01T21:45:39Z"}, {"size": 920, "ticker": "TSLA", "price": "391.52", "sale_cond_codes": null, "premium": "360198.40", "volume": 65175123, "executed_at": "2026-05-01T21:45:37Z", "canceled": false, "nbbo_ask": "391.45", "nbbo_bid": "391.44", "ext_hour_sold_codes": "extended_hours_trade", "market_center": "L", "nbbo_ask_quantity": 32, "nbbo_bid_quantity": 2, "tracking_id": 32431376389200, "trade_code": null, "trade_settlement": "regular", "trf_executed_at": "2026-05-01T21:45:37Z"}, {"size": 3100, "ticker": "SGOV", "price": "100.41", "sale_cond_codes": null, "premium": "311271.00", "volume": 33422075, "executed_at": "2026-05-01T21:45:31Z", "canceled": false, "nbbo_ask": "100.42", "nbbo_bid": "100.41", "ext_hour_sold_codes": "extended_hours_trade", "market_center": "L", "nbbo_ask_quantity": 137, "nbbo_bid_quantity": 239963, "tracking_id": 10204920626738, "trade_code": null, "trade_settlement": "regular", "trf_executed_at": "2026-05-01T21:45:31Z"}, {"size": 490, "ticker": "AVGO", "price": "419.9982", "sale_cond_codes": null, "premium": "205799.1180", "volume": 11867614, "executed_at": "2026-05-01T21:45:29Z", "canceled": false, "nbbo_ask": "420.1", "nbbo_bid": "419.55", "ext_hour_sold_codes": "extended_hours_trade", "market_center": "L", "nbbo_ask_quantity": 497, "nbbo_bid_quantity": 66, "tracking_id": 33414923891974, "trade_code": null, "trade_settlement": "regular", "trf_executed_at": "2026-05-01T21:45:29Z"}, {"size": 979, "ticker": "SOXL", "price": "129.77", "sale_cond_codes": null, "premium": "127044.83", "volume": 40627604, "executed_at": "2026-05-01T21:45:21Z", "canceled": false, "nbbo_ask": "129.81", "nbbo_bid": "129.77", "ext_hour_sold_codes": "extended_hours_trade", "market_center": "L", "nbbo_ask_quantity": 2, "nbbo_bid_quantity": 1, "tracking_id": 12760426157863, "trade_code": null, "trade_settlement": "regular", "trf_executed_at": "2026-05-01T21:45:21Z"}, {"size": 5000, "ticker": "TSLA", "price": "391.52", "sale_cond_codes": null, "premium": "1957600.00", "volume": 65174058, "executed_at": "2026-05-01T21:45:19Z", "canceled": false, "nbbo_ask": "391.46", "nbbo_bid": "391.44", "ext_hour_sold_codes": "extended_hours_trade", "market_center": "L", "nbbo_ask_quantity": 33, "nbbo_bid_quantity": 2, "tracking_id": 32431376371341, "trade_code": null, "trade_settlement": "regular", "trf_executed_at": "2026-05-01T21:45:19Z"}, {"size": 14614, "ticker": "SOUN", "price": "9.43", "sale_cond_codes": null, "premium": "137810.02", "volume": 68035217, "executed_at": "2026-05-01T21:45:13Z", "canceled": false, "nbbo_ask": "9.45", "nbbo_bid": "9.43", "ext_hour_sold_codes": "extended_hours_trade", "market_center": "L", "nbbo_ask_quantity": 27, "nbbo_bid_quantity": 2067, "tracking_id": 23132772169985, "trade_code": null, "trade_settlement": "regular", "trf_executed_at": "2026-05-01T21:45:13Z"}, {"size": 10761, "ticker": "SOXS", "price": "13.03", "sale_cond_codes": null, "premium": "140215.83", "volume": 123208672, "executed_at": "2026-05-01T21:45:09Z", "canceled": false, "nbbo_ask": "13.03", "nbbo_bid": "13.02", "ext_hour_sold_codes": "extended_hours_trade", "market_center": "L", "nbbo_ask_quantity": 76, "nbbo_bid_quantity": 632, "tracking_id": 12764721113410, "trade_code": null, "trade_settlement": "regular", "trf_executed_at": "2026-05-01T21:45:09Z"}, {"size": 240, "ticker": "QQQ", "price": "673.48", "sale_cond_codes": null, "premium": "161635.20", "volume": 38996030, "executed_at": "2026-05-01T21:45:08Z", "canceled": false, "nbbo_ask": "673.49", "nbbo_bid": "673.45", "ext_hour_sold_codes": "extended_hours_trade", "market_center": "L", "nbbo_ask_quantity": 1426, "nbbo_bid_quantity": 2, "tracking_id": 10501273347450, "trade_code": null, "trade_settlement": "regular", "trf_executed_at": "2026-05-01T21:45:08Z"}, {"size": 2000, "ticker": "BE", "price": "292.6", "sale_cond_codes": null, "premium": "585200.0", "volume": 9510313, "executed_at": "2026-05-01T21:45:07Z", "canceled": false, "nbbo_ask": "293", "nbbo_bid": "292.3", "ext_hour_sold_codes": "extended_hours_trade", "market_center": "L", "nbbo_ask_quantity": 118, "nbbo_bid_quantity": 20, "tracking_id": 39264669327557, "trade_code": null, "trade_settlement": "regular", "trf_executed_at": "2026-05-01T21:45:07Z"}, {"size": 500, "ticker": "AMZN", "price": "267.7928", "sale_cond_codes": null, "premium": "133896.4000", "volume": 50770458, "executed_at": "2026-05-01T21:45:01Z", "canceled": false, "nbbo_ask": "267.75", "nbbo_bid": "267.61", "ext_hour_sold_codes": "extended_hours_trade", "market_center": "L", "nbbo_ask_quantity": 8, "nbbo_bid_quantity": 4, "tracking_id": 30167928588525, "trade_code": null, "trade_settlement": "regular", "trf_executed_at": "2026-05-01T21:45:01Z"}, {"size": 200, "ticker": "SPY", "price": "720.13", "sale_cond_codes": null, "premium": "144026.00", "volume": 42673071, "executed_at": "2026-05-01T21:45:00Z", "canceled": false, "nbbo_ask": "720.18", "nbbo_bid": "719.77", "ext_hour_sold_codes": "extended_hours_trade", "market_center": "L", "nbbo_ask_quantity": 16, "nbbo_bid_quantity": 10, "tracking_id": 10509863273388, "trade_code": null, "trade_settlement": "regular", "trf_executed_at": "2026-05-01T21:45:00Z"}, {"size": 3700, "ticker": "GME", "price": "27.75", "sale_cond_codes": null, "premium": "102675.00", "volume": 17628390, "executed_at": "2026-05-01T21:44:58Z", "canceled": false, "nbbo_ask": "27.85", "nbbo_bid": "27.75", "ext_hour_sold_codes": "extended_hours_trade", "market_center": "L", "nbbo_ask_quantity": 100, "nbbo_bid_quantity": 404, "tracking_id": 32504390794620, "trade_code": null, "trade_settlement": "regular", "trf_executed_at": "2026-05-01T21:44:58Z"}, {"size": 600, "ticker": "GOOGL", "price": "384.92", "sale_cond_codes": null, "premium": "230952.00", "volume": 30051270, "executed_at": "2026-05-01T21:44:36Z", "canceled": false, "nbbo_ask": "384.92", "nbbo_bid": "384.78", "ext_hour_sold_codes": "extended_hours_trade", "market_center": "L", "nbbo_ask_quantity": 12623, "nbbo_bid_quantity": 120, "tracking_id": 32238102800462, "trade_code": null, "trade_settlement": "regular", "trf_executed_at": "2026-05-01T21:44:36Z"}, {"size": 5700, "ticker": "GME", "price": "27.8", "sale_cond_codes": null, "premium": "158460.0", "volume": 17595393, "executed_at": "2026-05-01T21:44:26Z", "canceled": false, "nbbo_ask": "27.85", "nbbo_bid": "27.76", "ext_hour_sold_codes": "extended_hours_trade", "market_center": "L", "nbbo_ask_quantity": 200, "nbbo_bid_quantity": 121, "tracking_id": 32504390762468, "trade_code": null, "trade_settlement": "regular", "trf_executed_at": "2026-05-01T21:44:26Z"}, {"size": 280, "ticker": "AMD", "price": "360.74", "sale_cond_codes": null, "premium": "101007.20", "volume": 34142102, "executed_at": "2026-05-01T21:44:16Z", "canceled": false, "nbbo_ask": "360.74", "nbbo_bid": "360.7", "ext_hour_sold_codes": "extended_hours_trade", "market_center": "L", "nbbo_ask_quantity": 100, "nbbo_bid_quantity": 58, "tracking_id": 25005377853416, "trade_code": null, "trade_settlement": "regular", "trf_executed_at": "2026-05-01T21:44:16Z"}, {"size": 11060, "ticker": "RDDT", "price": "167.9944", "sale_cond_codes": "average_price_trade", "premium": "1858018.0640", "volume": 14212350, "executed_at": "2026-05-01T21:44:07Z", "canceled": false, "nbbo_ask": "167.1", "nbbo_bid": "166.91", "ext_hour_sold_codes": "extended_hours_trade", "market_center": "L", "nbbo_ask_quantity": 25, "nbbo_bid_quantity": 500, "tracking_id": 19477754935053, "trade_code": null, "trade_settlement": "regular", "trf_executed_at": "2026-05-01T21:44:07Z"}, {"size": 286, "ticker": "AMD", "price": "360.65", "sale_cond_codes": null, "premium": "103145.90", "volume": 34141705, "executed_at": "2026-05-01T21:44:06Z", "canceled": false, "nbbo_ask": "360.74", "nbbo_bid": "360.62", "ext_hour_sold_codes": "extended_hours_trade", "market_center": "L", "nbbo_ask_quantity": 100, "nbbo_bid_quantity": 103, "tracking_id": 25005377844025, "trade_code": null, "trade_settlement": "regular", "trf_executed_at": "2026-05-01T21:44:06Z"}, {"size": 1200, "ticker": "USO", "price": "143.4999", "sale_cond_codes": null, "premium": "172199.8800", "volume": 12744006, "executed_at": "2026-05-01T21:44:01Z", "canceled": false, "nbbo_ask": "143.5", "nbbo_bid": "143.4", "ext_hour_sold_codes": "extended_hours_trade", "market_center": "L", "nbbo_ask_quantity": 1, "nbbo_bid_quantity": 30, "tracking_id": 10307999752195, "trade_code": null, "trade_settlement": "regular", "trf_executed_at": "2026-05-01T21:44:01Z"}, {"size": 1000, "ticker": "MU", "price": "540.2", "sale_cond_codes": null, "premium": "540200.0", "volume": 40096515, "executed_at": "2026-05-01T21:43:48Z", "canceled": false, "nbbo_ask": "540.3", "nbbo_bid": "540.01", "ext_hour_sold_codes": "extended_hours_trade", "market_center": "L", "nbbo_ask_quantity": 1, "nbbo_bid_quantity": 5, "tracking_id": 27389084675012, "trade_code": null, "trade_settlement": "regular", "trf_executed_at": "2026-05-01T21:43:48Z"}, {"size": 14256, "ticker": "SOUN", "price": "9.4417", "sale_cond_codes": null, "premium": "134600.8752", "volume": 68006556, "executed_at": "2026-05-01T21:43:45Z", "canceled": false, "nbbo_ask": "9.45", "nbbo_bid": "9.43", "ext_hour_sold_codes": "extended_hours_trade", "market_center": "L", "nbbo_ask_quantity": 289, "nbbo_bid_quantity": 2061, "tracking_id": 23132772081463, "trade_code": null, "trade_settlement": "regular", "trf_executed_at": "2026-05-01T21:43:45Z"}, {"size": 763, "ticker": "NVDA", "price": "198.31", "sale_cond_codes": null, "premium": "151310.53", "volume": 128172758, "executed_at": "2026-05-01T21:43:34Z", "canceled": false, "nbbo_ask": "198.28", "nbbo_bid": "198.25", "ext_hour_sold_codes": "extended_hours_trade", "market_center": "L", "nbbo_ask_quantity": 17, "nbbo_bid_quantity": 1, "tracking_id": 30575950394824, "trade_code": null, "trade_settlement": "regular", "trf_executed_at": "2026-05-01T21:43:34Z"}, {"size": 1500, "ticker": "SPY", "price": "720.1", "sale_cond_codes": null, "premium": "1080150.0", "volume": 42672454, "executed_at": "2026-05-01T21:43:27Z", "canceled": false, "nbbo_ask": "720.18", "nbbo_bid": "719.77", "ext_hour_sold_codes": "extended_hours_trade", "market_center": "L", "nbbo_ask_quantity": 16, "nbbo_bid_quantity": 10, "tracking_id": 10509863180405, "trade_code": null, "trade_settlement": "regular", "trf_executed_at": "2026-05-01T21:43:27Z"}, {"size": 1100, "ticker": "IWM", "price": "278.52", "sale_cond_codes": null, "premium": "306372.00", "volume": 28904479, "executed_at": "2026-05-01T21:43:21Z", "canceled": false, "nbbo_ask": "278.96", "nbbo_bid": "278.46", "ext_hour_sold_codes": "extended_hours_trade", "market_center": "L", "nbbo_ask_quantity": 300, "nbbo_bid_quantity": 300, "tracking_id": 11746813755674, "trade_code": null, "trade_settlement": "regular", "trf_executed_at": "2026-05-01T21:43:21Z"}, {"size": 1035, "ticker": "EBAY", "price": "117.7", "sale_cond_codes": null, "premium": "121819.5", "volume": 11061882, "executed_at": "2026-05-01T21:43:10Z", "canceled": false, "nbbo_ask": "117.7", "nbbo_bid": "117.11", "ext_hour_sold_codes": "extended_hours_trade", "market_center": "L", "nbbo_ask_quantity": 4300, "nbbo_bid_quantity": 1, "tracking_id": 30859418212436, "trade_code": null, "trade_settlement": "regular", "trf_executed_at": "2026-05-01T21:43:10Z"}, {"size": 6777, "ticker": "IBIT", "price": "44.32", "sale_cond_codes": null, "premium": "300356.64", "volume": 45944162, "executed_at": "2026-05-01T21:43:07Z", "canceled": false, "nbbo_ask": "44.4", "nbbo_bid": "44.32", "ext_hour_sold_codes": "extended_hours_trade", "market_center": "L", "nbbo_ask_quantity": 5, "nbbo_bid_quantity": 354, "tracking_id": 4372354895251, "trade_code": null, "trade_settlement": "regular", "trf_executed_at": "2026-05-01T21:43:07Z"}, {"size": 6777, "ticker": "IBIT", "price": "44.32", "sale_cond_codes": null, "premium": "300356.64", "volume": 45937339, "executed_at": "2026-05-01T21:43:03Z", "canceled": false, "nbbo_ask": "44.4", "nbbo_bid": "44.32", "ext_hour_sold_codes": "extended_hours_trade", "market_center": "L", "nbbo_ask_quantity": 5, "nbbo_bid_quantity": 400, "tracking_id": 4372354890374, "trade_code": null, "trade_settlement": "regular", "trf_executed_at": "2026-05-01T21:43:03Z"}, {"size": 370, "ticker": "AVGO", "price": "420.1", "sale_cond_codes": null, "premium": "155437.0", "volume": 11866241, "executed_at": "2026-05-01T21:42:55Z", "canceled": false, "nbbo_ask": "420.48", "nbbo_bid": "420.1", "ext_hour_sold_codes": "extended_hours_trade", "market_center": "L", "nbbo_ask_quantity": 402, "nbbo_bid_quantity": 40, "tracking_id": 33414923738482, "trade_code": null, "trade_settlement": "regular", "trf_executed_at": "2026-05-01T21:42:55Z"}, {"size": 597, "ticker": "MSTR", "price": "176.8467", "sale_cond_codes": null, "premium": "105577.4799", "volume": 21490599, "executed_at": "2026-05-01T21:42:41Z", "canceled": false, "nbbo_ask": "177.2", "nbbo_bid": "177.11", "ext_hour_sold_codes": "extended_hours_trade", "market_center": "L", "nbbo_ask_quantity": 10, "nbbo_bid_quantity": 5, "tracking_id": 30666144655000, "trade_code": null, "trade_settlement": "regular", "trf_executed_at": "2026-05-01T21:42:41Z"}, {"size": 875, "ticker": "SNXX", "price": "117.48", "sale_cond_codes": null, "premium": "102795.00", "volume": 17461218, "executed_at": "2026-05-01T21:42:39Z", "canceled": false, "nbbo_ask": "117.5", "nbbo_bid": "116.7", "ext_hour_sold_codes": "extended_hours_trade", "market_center": "L", "nbbo_ask_quantity": 89, "nbbo_bid_quantity": 10, "tracking_id": 146003196419548, "trade_code": null, "trade_settlement": "regular", "trf_executed_at": "2026-05-01T21:42:39Z"}, {"size": 1000, "ticker": "EBAY", "price": "115.7034", "sale_cond_codes": null, "premium": "115703.4000", "volume": 11016526, "executed_at": "2026-05-01T21:42:39Z", "canceled": false, "nbbo_ask": "116", "nbbo_bid": "115.81", "ext_hour_sold_codes": "extended_hours_trade", "market_center": "L", "nbbo_ask_quantity": 350, "nbbo_bid_quantity": 100, "tracking_id": 30859418180907, "trade_code": null, "trade_settlement": "regular", "trf_executed_at": "2026-05-01T21:42:39Z"}, {"size": 100, "ticker": "SNDK", "price": "1189.7398", "sale_cond_codes": null, "premium": "118973.9800", "volume": 22989583, "executed_at": "2026-05-01T21:42:26Z", "canceled": false, "nbbo_ask": "1190.9", "nbbo_bid": "1188.03", "ext_hour_sold_codes": "extended_hours_trade", "market_center": "L", "nbbo_ask_quantity": 41, "nbbo_bid_quantity": 6, "tracking_id": 18270869023829, "trade_code": null, "trade_settlement": "regular", "trf_executed_at": "2026-05-01T21:42:26Z"}, {"size": 1000, "ticker": "EBAY", "price": "115.5893", "sale_cond_codes": null, "premium": "115589.3000", "volume": 11009394, "executed_at": "2026-05-01T21:42:21Z", "canceled": false, "nbbo_ask": "115.59", "nbbo_bid": "115.2", "ext_hour_sold_codes": "extended_hours_trade", "market_center": "L", "nbbo_ask_quantity": 310, "nbbo_bid_quantity": 5, "tracking_id": 30859418163655, "trade_code": null, "trade_settlement": "regular", "trf_executed_at": "2026-05-01T21:42:21Z"}, {"size": 100, "ticker": "SNDK", "price": "1188.4784", "sale_cond_codes": null, "premium": "118847.8400", "volume": 22989207, "executed_at": "2026-05-01T21:42:21Z", "canceled": false, "nbbo_ask": "1190.9", "nbbo_bid": "1188.03", "ext_hour_sold_codes": "extended_hours_trade", "market_center": "L", "nbbo_ask_quantity": 41, "nbbo_bid_quantity": 6, "tracking_id": 18270869018381, "trade_code": null, "trade_settlement": "regular", "trf_executed_at": "2026-05-01T21:42:21Z"}, {"size": 96, "ticker": "SNDK", "price": "1188.45", "sale_cond_codes": null, "premium": "114091.20", "volume": 22988907, "executed_at": "2026-05-01T21:42:19Z", "canceled": false, "nbbo_ask": "1190.9", "nbbo_bid": "1188.03", "ext_hour_sold_codes": "extended_hours_trade", "market_center": "L", "nbbo_ask_quantity": 41, "nbbo_bid_quantity": 6, "tracking_id": 18270869016545, "trade_code": null, "trade_settlement": "regular", "trf_executed_at": "2026-05-01T21:42:19Z"}, {"size": 1000, "ticker": "SGOV", "price": "100.41", "sale_cond_codes": null, "premium": "100410.00", "volume": 33411021, "executed_at": "2026-05-01T21:42:14Z", "canceled": false, "nbbo_ask": "100.42", "nbbo_bid": "100.41", "ext_hour_sold_codes": "extended_hours_trade", "market_center": "L", "nbbo_ask_quantity": 137, "nbbo_bid_quantity": 240001, "tracking_id": 10204920430183, "trade_code": null, "trade_settlement": "regular", "trf_executed_at": "2026-05-01T21:42:14Z"}, {"size": 90, "ticker": "SNDK", "price": "1189.2", "sale_cond_codes": null, "premium": "107028.0", "volume": 22988730, "executed_at": "2026-05-01T21:42:07Z", "canceled": false, "nbbo_ask": "1190.9", "nbbo_bid": "1189", "ext_hour_sold_codes": "extended_hours_trade", "market_center": "L", "nbbo_ask_quantity": 41, "nbbo_bid_quantity": 43, "tracking_id": 18270869004299, "trade_code": null, "trade_settlement": "regular", "trf_executed_at": "2026-05-01T21:42:07Z"}, {"size": 520, "ticker": "COHR", "price": "332", "sale_cond_codes": null, "premium": "172640", "volume": 4611514, "executed_at": "2026-05-01T21:42:02Z", "canceled": false, "nbbo_ask": "332", "nbbo_bid": "330.9", "ext_hour_sold_codes": "extended_hours_trade", "market_center": "L", "nbbo_ask_quantity": 125, "nbbo_bid_quantity": 1, "tracking_id": 28230898158674, "trade_code": null, "trade_settlement": "regular", "trf_executed_at": "2026-05-01T21:42:02Z"}, {"size": 299, "ticker": "TSLA", "price": "391.4301", "sale_cond_codes": null, "premium": "117037.5999", "volume": 65158474, "executed_at": "2026-05-01T21:42:01Z", "canceled": false, "nbbo_ask": "391.46", "nbbo_bid": "391.43", "ext_hour_sold_codes": "extended_hours_trade", "market_center": "L", "nbbo_ask_quantity": 28, "nbbo_bid_quantity": 79, "tracking_id": 32431376173620, "trade_code": null, "trade_settlement": "regular", "trf_executed_at": "2026-05-01T21:42:01Z"}, {"size": 299, "ticker": "TSLA", "price": "391.43", "sale_cond_codes": null, "premium": "117037.57", "volume": 65158773, "executed_at": "2026-05-01T21:42:01Z", "canceled": false, "nbbo_ask": "391.46", "nbbo_bid": "391.43", "ext_hour_sold_codes": "extended_hours_trade", "market_center": "L", "nbbo_ask_quantity": 28, "nbbo_bid_quantity": 79, "tracking_id": 32431376173620, "trade_code": null, "trade_settlement": "regular", "trf_executed_at": "2026-05-01T21:42:01Z"}, {"size": 281, "ticker": "META", "price": "608.66", "sale_cond_codes": null, "premium": "171033.46", "volume": 21331694, "executed_at": "2026-05-01T21:41:50Z", "canceled": false, "nbbo_ask": "608.95", "nbbo_bid": "608.65", "ext_hour_sold_codes": "extended_hours_trade", "market_center": "L", "nbbo_ask_quantity": 35, "nbbo_bid_quantity": 10, "tracking_id": 32508685574287, "trade_code": null, "trade_settlement": "regular", "trf_executed_at": "2026-05-01T21:41:50Z"}, {"size": 1133, "ticker": "SPY", "price": "720.1", "sale_cond_codes": null, "premium": "815873.3", "volume": 42670405, "executed_at": "2026-05-01T21:41:49Z", "canceled": false, "nbbo_ask": "720.13", "nbbo_bid": "719.77", "ext_hour_sold_codes": "extended_hours_trade", "market_center": "L", "nbbo_ask_quantity": 100, "nbbo_bid_quantity": 10, "tracking_id": 10509863082940, "trade_code": null, "trade_settlement": "regular", "trf_executed_at": "2026-05-01T21:41:49Z"}, {"size": 15200, "ticker": "SOFI", "price": "16.4", "sale_cond_codes": null, "premium": "249280.0", "volume": 78806706, "executed_at": "2026-05-01T21:41:46Z", "canceled": false, "nbbo_ask": "16.41", "nbbo_bid": "16.4", "ext_hour_sold_codes": "extended_hours_trade", "market_center": "L", "nbbo_ask_quantity": 440, "nbbo_bid_quantity": 25, "tracking_id": 24124909407862, "trade_code": null, "trade_settlement": "regular", "trf_executed_at": "2026-05-01T21:41:46Z"}, {"size": 3000, "ticker": "TQQQ", "price": "65.0687", "sale_cond_codes": null, "premium": "195206.1000", "volume": 67379155, "executed_at": "2026-05-01T21:41:45Z", "canceled": false, "nbbo_ask": "65.07", "nbbo_bid": "65.06", "ext_hour_sold_codes": "extended_hours_trade", "market_center": "L", "nbbo_ask_quantity": 1, "nbbo_bid_quantity": 33, "tracking_id": 12953699470398, "trade_code": null, "trade_settlement": "regular", "trf_executed_at": "2026-05-01T21:41:45Z"}, {"size": 1441, "ticker": "CRDO", "price": "184.85", "sale_cond_codes": null, "premium": "266368.85", "volume": 4678257, "executed_at": "2026-05-01T21:41:45Z", "canceled": false, "nbbo_ask": "184.95", "nbbo_bid": "184.1", "ext_hour_sold_codes": "extended_hours_trade", "market_center": "L", "nbbo_ask_quantity": 40, "nbbo_bid_quantity": 108, "tracking_id": 21122727266892, "trade_code": null, "trade_settlement": "regular", "trf_executed_at": "2026-05-01T21:41:45Z"}, {"size": 1798, "ticker": "INTC", "price": "99.91", "sale_cond_codes": null, "premium": "179638.18", "volume": 157234906, "executed_at": "2026-05-01T21:41:44Z", "canceled": false, "nbbo_ask": "99.93", "nbbo_bid": "99.91", "ext_hour_sold_codes": "extended_hours_trade", "market_center": "L", "nbbo_ask_quantity": 164, "nbbo_bid_quantity": 299, "tracking_id": 25812831553881, "trade_code": null, "trade_settlement": "regular", "trf_executed_at": "2026-05-01T21:41:44Z"}, {"size": 7411, "ticker": "QBTX", "price": "13.89", "sale_cond_codes": null, "premium": "102938.79", "volume": 1785417, "executed_at": "2026-05-01T21:41:41Z", "canceled": false, "nbbo_ask": "14.12", "nbbo_bid": "13.89", "ext_hour_sold_codes": "extended_hours_trade", "market_center": "L", "nbbo_ask_quantity": 100, "nbbo_bid_quantity": 100, "tracking_id": 4373068872, "trade_code": null, "trade_settlement": "regular", "trf_executed_at": "2026-05-01T21:41:41Z"}, {"size": 5702, "ticker": "GME", "price": "28", "sale_cond_codes": null, "premium": "159656", "volume": 17386513, "executed_at": "2026-05-01T21:41:37Z", "canceled": false, "nbbo_ask": "28.09", "nbbo_bid": "28.03", "ext_hour_sold_codes": "extended_hours_trade", "market_center": "L", "nbbo_ask_quantity": 198, "nbbo_bid_quantity": 100, "tracking_id": 32504390593501, "trade_code": null, "trade_settlement": "regular", "trf_executed_at": "2026-05-01T21:41:37Z"}, {"size": 3800, "ticker": "GME", "price": "28", "sale_cond_codes": null, "premium": "106400", "volume": 17380811, "executed_at": "2026-05-01T21:41:37Z", "canceled": false, "nbbo_ask": "28.09", "nbbo_bid": "28.03", "ext_hour_sold_codes": "extended_hours_trade", "market_center": "L", "nbbo_ask_quantity": 198, "nbbo_bid_quantity": 100, "tracking_id": 32504390593500, "trade_code": null, "trade_settlement": "regular", "trf_executed_at": "2026-05-01T21:41:37Z"}, {"size": 905, "ticker": "EBAY", "price": "116", "sale_cond_codes": null, "premium": "104980", "volume": 10990035, "executed_at": "2026-05-01T21:41:34Z", "canceled": false, "nbbo_ask": "116", "nbbo_bid": "115.15", "ext_hour_sold_codes": "extended_hours_trade", "market_center": "L", "nbbo_ask_quantity": 800, "nbbo_bid_quantity": 5, "tracking_id": 30859418116483, "trade_code": null, "trade_settlement": "regular", "trf_executed_at": "2026-05-01T21:41:34Z"}, {"size": 14986, "ticker": "SNDU", "price": "71.19", "sale_cond_codes": null, "premium": "1066853.34", "volume": 1723214, "executed_at": "2026-05-01T21:41:33Z", "canceled": false, "nbbo_ask": "72", "nbbo_bid": "67.3", "ext_hour_sold_codes": "extended_hours_trade", "market_center": "L", "nbbo_ask_quantity": 89, "nbbo_bid_quantity": 1, "tracking_id": 1699166449802752, "trade_code": null, "trade_settlement": "regular", "trf_executed_at": "2026-05-01T21:41:33Z"}, {"size": 138, "ticker": "STX", "price": "728.48", "sale_cond_codes": null, "premium": "100530.24", "volume": 7362799, "executed_at": "2026-05-01T21:41:17Z", "canceled": false, "nbbo_ask": "728.5", "nbbo_bid": "727.55", "ext_hour_sold_codes": "extended_hours_trade", "market_center": "L", "nbbo_ask_quantity": 25, "nbbo_bid_quantity": 3, "tracking_id": 31602447441113, "trade_code": null, "trade_settlement": "regular", "trf_executed_at": "2026-05-01T21:41:17Z"}, {"size": 2000, "ticker": "EBAY", "price": "116.27", "sale_cond_codes": null, "premium": "232540.00", "volume": 10970211, "executed_at": "2026-05-01T21:41:15Z", "canceled": false, "nbbo_ask": "116.28", "nbbo_bid": "115.11", "ext_hour_sold_codes": "extended_hours_trade", "market_center": "L", "nbbo_ask_quantity": 2300, "nbbo_bid_quantity": 100, "tracking_id": 30859418097720, "trade_code": null, "trade_settlement": "regular", "trf_executed_at": "2026-05-01T21:41:15Z"}, {"size": 625, "ticker": "SNDK", "price": "1190", "sale_cond_codes": null, "premium": "743750", "volume": 22988382, "executed_at": "2026-05-01T21:41:11Z", "canceled": false, "nbbo_ask": "1190.45", "nbbo_bid": "1190.4", "ext_hour_sold_codes": "extended_hours_trade", "market_center": "L", "nbbo_ask_quantity": 1, "nbbo_bid_quantity": 5, "tracking_id": 18270868948772, "trade_code": null, "trade_settlement": "regular", "trf_executed_at": "2026-05-01T21:41:11Z"}, {"size": 2400, "ticker": "INTC", "price": "99.91", "sale_cond_codes": null, "premium": "239784.00", "volume": 157228004, "executed_at": "2026-05-01T21:41:07Z", "canceled": false, "nbbo_ask": "99.92", "nbbo_bid": "99.9", "ext_hour_sold_codes": "extended_hours_trade", "market_center": "L", "nbbo_ask_quantity": 154, "nbbo_bid_quantity": 101, "tracking_id": 25812831516931, "trade_code": null, "trade_settlement": "regular", "trf_executed_at": "2026-05-01T21:41:07Z"}]